Workbook
Name BBDD: [1]BBDD!$A$2:$W$109
Name BBDD: #REF!
Name EAN: [1]EAN!$A$3:$C$8547
Name EAN: EAN!$A$3:$C$8547
Name ENVIO: #REF!
Name ENVIO: #REF!
Name PVP: #REF!
Name PVP: #REF!
Name TP: '[1]T.P.'!$A$2:$B$3
Name TP: 'T.P.'!$A$2:$B$3

Sheet RESUMEN PEDIDO
B1: KIN COSMETICS, S.A.U. | J1: EDICIÓN FEBRERO 2026
B2: HOJA DE PEDIDO DISTRIBUIDOR
H3: Nº PEDIDO:
H4: Nº FACTURA:
H5: FECHA FACTURA:
B6: DATOS
B8: FECHA PEDIDO
B9: =NOW() -> 46079.371
B11: DATOS CLIENTE
B12: CÓD. CLIENTE | D12: NOMBRE | E12: =VLOOKUP(C12,'BBDD ACTUALITZADA'!A2:O103,2,FALSE) -> #N/A
B13: DIRECCIÓN | C13: =VLOOKUP(C12,'BBDD ACTUALITZADA'!A2:O103,4,FALSE) -> #N/A
B14: POBLACIÓN | C14: =VLOOKUP(C12,'BBDD ACTUALITZADA'!A2:O103,6,FALSE) -> #N/A | H14: C.P. | J14: =VLOOKUP(C12,'BBDD ACTUALITZADA'!A2:O103,5,FALSE) -> #N/A
B15: PROVÍNCIA | C15: =VLOOKUP(C12,'BBDD ACTUALITZADA'!A2:O103,7,FALSE) -> #N/A | H15: TELÉFONO | J15: =VLOOKUP(C12,'BBDD ACTUALITZADA'!A2:O103,8,FALSE) -> #N/A
B16: PAÍS | C16: =VLOOKUP(C12,'BBDD ACTUALITZADA'!A2:P103,16) -> #N/A
B18: DATOS ENVÍO
B19: DIRECCIÓN | C19: =VLOOKUP(C12,'BBDD ACTUALITZADA'!A2:P103,4,FALSE) -> #N/A
B20: DIRECCIÓN 2 | C20: =VLOOKUP(C12,BBDD,21,0) -> #REF!
B21: POBLACIÓN | C21: =VLOOKUP(C12,'BBDD ACTUALITZADA'!A9:O110,6,FALSE) -> #N/A | H21: C.P. | J21: =VLOOKUP(C12,'BBDD ACTUALITZADA'!A9:O110,5,FALSE) -> #N/A
B22: PROVÍNCIA | C22: =VLOOKUP(C12,'BBDD ACTUALITZADA'!A9:O110,7,FALSE) -> #N/A | H22: TELÉFONO | J22: =J15 -> #N/A
B23: PAÍS | C23: =C16 -> #N/A
B25: ASESOR COMERCIAL
B26: CÓDIGO | C26: =VLOOKUP(C12,'BBDD ACTUALITZADA'!A2:P103,10,FALSE) -> #N/A | D26: NOMBRE | E26: =VLOOKUP(C12,'BBDD ACTUALITZADA'!A2:Q103,17,FALSE) -> #N/A
B28: DESCUENTO CLIENTE
B29: DESCUENTO 1
B30: DESCUENTO 2
B31: DTO. MAT. MKT | C31: 0.7
B33: RESUMEN PEDIDO
B35: SUBTOTAL PRODUCTO TÉCNICO | J35: ='PRODUCTO TÉCNICO'!M7 -> 0
B36: SUBTOTAL PRODUCTO REVENTA | J36: ='PRODUCTO REVENTA'!M7 -> 0
B37: SUBTOTAL PRODUCTOS | J37: =J35+J36 -> 0
B38: SUBTOTAL PROMOCIONES (no acumula para Material Marketing)
C41: CRÉDITO EN MATERIAL DE MARKETING | G41: 0.03 | H41: =(J37-J38)*G41 -> 0
C43: CRÉDITO EN MATERIAL DE MARKETING GASTADO | H43: ='MATERIAL MARKETING'!H7+'MATERIAL MKT OUTLET'!G7 -> 0
C45: *TOTAL MATERIAL DE MARKETING | H45: =H41-H43 -> 0 | J45: =IF(H45<0,"A PAGAR",IF(H45>0,"A COMPENSAR","COMPENSADO")) -> COMPENSADO
B47: *El importe pendiente a compensar, no es acumulativo y tampoco se abona.
B49: RESUMEN PEDIDO OUTLET
B51: SUBTOTAL OUTLET (acumula para Material Marketing Outlet) | J51: ='PRODUCTO OUTLET'!J7 -> 0
C54: CRÉDITO EN MATERIAL DE MARKETING | H54: =J51*G54 -> 0
C56: CRÉDITO EN MATERIAL DE MARKETING GASTADO | H56: ='MATERIAL MKT OUTLET'!G7 -> 0
C58: *TOTAL MATERIAL DE MARKETING | H58: =H54-H56 -> 0 | J58: =IF(H58<0,"A PAGAR",IF(H58>0,"A COMPENSAR","COMPENSADO")) -> COMPENSADO
B60: *El importe pendiente a compensar, no es acumulativo y tampoco se abona.
B62: SUBTOTAL PEDIDO | J62: =J37+J51 -> 0
B63: DESCUENTO P.P. | D63: BASE IMPONIBLE | F63: IVA % | H63: R.E. | J63: TOTAL PEDIDO
B64: =VLOOKUP(C12,#REF!,7,0) -> #REF! | C64: =J62*B64 -> #REF! | D64: =J62-C64 -> #REF! | F64: 0.21 | G64: =D64*F64 -> #REF! | H64: =VLOOKUP(C12,#REF!,8,0) -> #REF! | I64: 0 | J64: =(J62-C64)+G64+I64 -> #REF!
B65: FORMA DE PAGO | F65: TÉRMINO DE PAGO
B66: CÓDIGO F.P. | C66: 2 | D66: RECIBO BANCARIO | F66: CÓDIGO T.P. | H66: 3 | J66: =VLOOKUP(H66,TP,2,0) -> 30 DÍAS
B68: COMENTARIOS:

Sheet PRODUCTO TÉCNICO
B1: KIN COSMETICS, S.A.U.
B2: HOJA DE PEDIDO DISTRIBUIDOR
B6: PRODUCTO TÉCNICO
B7: SUBTOTAL PRODUCTO TÉCNICO | D7: =D9+D133+D223+D231+D240+D252+D260+D267+D271+D277+D279+D302+D203+D249 -> 0 | J7: =SUBTOTAL(9,J10:J132,J134:J202,J204:J222,J224:J230,J232:J239,J241:J248,J250:J251,J268:J270,J253:J259,J272:J276,J261:J266,J278:J278,J280:J301,J303:J309) -> 0 | M7: =SUBTOTAL(9,M9:M309) -> 0
B8: Ref. | C8: Descripción | D8: Unidades | E8: Precio Tarifa | F8: PVP | G8: Código EAN | H8: Formato | I8: Packing | J8: Cajas | K8: Dto. 1% | L8: Dto. 2% | M8: Subtotal
B9: KINCREM COLOR / COLORACIÓN | D9: =SUM(D10:D132) -> 0 | I9: 12 | J9: =D9/I9 -> 0
B10: 502001 | C10: KINCREM COLOR 1.0 | E10: 36.9 | F10: 40.6 | G10: =VLOOKUP(B10,EAN,3,0) -> 8435057015233 | H10: 3 x 100 ml | I10: 12 | J10: =D10/I10 -> 0 | K10: ='RESUMEN PEDIDO'!$C$29 -> 0 | L10: ='RESUMEN PEDIDO'!$C$30 -> 0 | M10: =(D10*(E10-(E10*K10)))-(D10*(E10-(E10*K10)))*L10 -> 0
B11: 502002 | C11: KINCREM COLOR 2.0 | E11: 36.9 | F11: 40.6 | G11: =VLOOKUP(B11,EAN,3,0) -> 8435057015240 | H11: 3 x 100 ml | I11: 12 | J11: =D11/I11 -> 0 | K11: ='RESUMEN PEDIDO'!$C$29 -> 0 | L11: ='RESUMEN PEDIDO'!$C$30 -> 0 | M11: =(D11*(E11-(E11*K11)))-(D11*(E11-(E11*K11)))*L11 -> 0
B12: 502003 | C12: KINCREM COLOR 3.0 | E12: 36.9 | F12: 40.6 | G12: =VLOOKUP(B12,EAN,3,0) -> 8435057015257 | H12: 3 x 100 ml | I12: 12 | J12: =D12/I12 -> 0 | K12: ='RESUMEN PEDIDO'!$C$29 -> 0 | L12: ='RESUMEN PEDIDO'!$C$30 -> 0 | M12: =(D12*(E12-(E12*K12)))-(D12*(E12-(E12*K12)))*L12 -> 0
B13: 502004 | C13: KINCREM COLOR 4.0 | E13: 36.9 | F13: 40.6 | G13: =VLOOKUP(B13,EAN,3,0) -> 8435057015264 | H13: 3 x 100 ml | I13: 12 | J13: =D13/I13 -> 0 | K13: ='RESUMEN PEDIDO'!$C$29 -> 0 | L13: ='RESUMEN PEDIDO'!$C$30 -> 0 | M13: =(D13*(E13-(E13*K13)))-(D13*(E13-(E13*K13)))*L13 -> 0
B14: 502005 | C14: KINCREM COLOR 5.0 | E14: 36.9 | F14: 40.6 | G14: =VLOOKUP(B14,EAN,3,0) -> 8435057015271 | H14: 3 x 100 ml | I14: 12 | J14: =D14/I14 -> 0 | K14: ='RESUMEN PEDIDO'!$C$29 -> 0 | L14: ='RESUMEN PEDIDO'!$C$30 -> 0 | M14: =(D14*(E14-(E14*K14)))-(D14*(E14-(E14*K14)))*L14 -> 0
B15: 502006 | C15: KINCREM COLOR 6.0 | E15: 36.9 | F15: 40.6 | G15: =VLOOKUP(B15,EAN,3,0) -> 8435057015288 | H15: 3 x 100 ml | I15: 12 | J15: =D15/I15 -> 0 | K15: ='RESUMEN PEDIDO'!$C$29 -> 0 | L15: ='RESUMEN PEDIDO'!$C$30 -> 0 | M15: =(D15*(E15-(E15*K15)))-(D15*(E15-(E15*K15)))*L15 -> 0
B16: 502007 | C16: KINCREM COLOR 7.0 | E16: 36.9 | F16: 40.6 | G16: =VLOOKUP(B16,EAN,3,0) -> 8435057015295 | H16: 3 x 100 ml | I16: 12 | J16: =D16/I16 -> 0 | K16: ='RESUMEN PEDIDO'!$C$29 -> 0 | L16: ='RESUMEN PEDIDO'!$C$30 -> 0 | M16: =(D16*(E16-(E16*K16)))-(D16*(E16-(E16*K16)))*L16 -> 0
B17: 502008 | C17: KINCREM COLOR 8.0 | E17: 36.9 | F17: 40.6 | G17: =VLOOKUP(B17,EAN,3,0) -> 8435057015301 | H17: 3 x 100 ml | I17: 12 | J17: =D17/I17 -> 0 | K17: ='RESUMEN PEDIDO'!$C$29 -> 0 | L17: ='RESUMEN PEDIDO'!$C$30 -> 0 | M17: =(D17*(E17-(E17*K17)))-(D17*(E17-(E17*K17)))*L17 -> 0
B18: 502009 | C18: KINCREM COLOR 9.0 | E18: 36.9 | F18: 40.6 | G18: =VLOOKUP(B18,EAN,3,0) -> 8435057015318 | H18: 3 x 100 ml | I18: 12 | J18: =D18/I18 -> 0 | K18: ='RESUMEN PEDIDO'!$C$29 -> 0 | L18: ='RESUMEN PEDIDO'!$C$30 -> 0 | M18: =(D18*(E18-(E18*K18)))-(D18*(E18-(E18*K18)))*L18 -> 0
B19: 502010 | C19: KINCREM COLOR 10.0 | E19: 36.9 | F19: 40.6 | G19: =VLOOKUP(B19,EAN,3,0) -> 8435057015325 | H19: 3 x 100 ml | I19: 12 | J19: =D19/I19 -> 0 | K19: ='RESUMEN PEDIDO'!$C$29 -> 0 | L19: ='RESUMEN PEDIDO'!$C$30 -> 0 | M19: =(D19*(E19-(E19*K19)))-(D19*(E19-(E19*K19)))*L19 -> 0
B20: 502011 | C20: KINCREM COLOR 3.00 | E20: 36.9 | F20: 40.6 | G20: =VLOOKUP(B20,EAN,3,0) -> 8435057015332 | H20: 3 x 100 ml | I20: 12 | J20: =D20/I20 -> 0 | K20: ='RESUMEN PEDIDO'!$C$29 -> 0 | L20: ='RESUMEN PEDIDO'!$C$30 -> 0 | M20: =(D20*(E20-(E20*K20)))-(D20*(E20-(E20*K20)))*L20 -> 0
B21: 502012 | C21: KINCREM COLOR 4.00 | E21: 36.9 | F21: 40.6 | G21: =VLOOKUP(B21,EAN,3,0) -> 8435057015349 | H21: 3 x 100 ml | I21: 12 | J21: =D21/I21 -> 0 | K21: ='RESUMEN PEDIDO'!$C$29 -> 0 | L21: ='RESUMEN PEDIDO'!$C$30 -> 0 | M21: =(D21*(E21-(E21*K21)))-(D21*(E21-(E21*K21)))*L21 -> 0
... B129: 502120 | C129: KINCREM COLOR M/99 | E129: 36.9 | F129: 40.6 | G129: =VLOOKUP(B129,EAN,3,0) -> 8435057016421 | H129: 3 x 100 ml | I129: 12 | J129: =D129/I129 -> 0 | K129: ='RESUMEN PEDIDO'!$C$29 -> 0 | L129: ='RESUMEN PEDIDO'!$C$30 -> 0 | M129: =(D129*(E129-(E129*K129)))-(D129*(E129-(E129*K129)))*L129 -> 0
B130: 502154 | C130: KINCREM COLOR 5.521 - MOCHA MOUSSE COLLECTION | E130: 36.9 | F130: 40.6 | G130: 8435057020350 | H130: 3 x 100 ml | I130: 12 | J130: =D130/I130 -> 0 | K130: ='RESUMEN PEDIDO'!$C$29 -> 0 | L130: ='RESUMEN PEDIDO'!$C$30 -> 0 | M130: =(D130*(E130-(E130*K130)))-(D130*(E130-(E130*K130)))*L130 -> 0
B131: 502155 | C131: KINCREM COLOR 7.521 - MOCHA MOUSSE COLLECTION | E131: 36.9 | F131: 40.6 | G131: 8435057020367 | H131: 3 x 100 ml | I131: 12 | J131: =D131/I131 -> 0 | K131: ='RESUMEN PEDIDO'!$C$29 -> 0 | L131: ='RESUMEN PEDIDO'!$C$30 -> 0 | M131: =(D131*(E131-(E131*K131)))-(D131*(E131-(E131*K131)))*L131 -> 0
B132: 502156 | C132: KINCREM COLOR 8.521 - MOCHA MOUSSE COLLECTION | E132: 36.9 | F132: 40.6 | G132: 8435057020344 | H132: 3 x 100 ml | I132: 12 | J132: =D132/I132 -> 0 | K132: ='RESUMEN PEDIDO'!$C$29 -> 0 | L132: ='RESUMEN PEDIDO'!$C$30 -> 0 | M132: =(D132*(E132-(E132*K132)))-(D132*(E132-(E132*K132)))*L132 -> 0
B133: KINESSENCES COLOR / COLORACIÓN | D133: =SUM(D134:D202) -> 0 | I133: 12 | J133: =D133/I133 -> 0
B134: 513101 | C134: KINESSENCES COLOR 1.0 | E134: 36.9 | F134: 40.6 | G134: =VLOOKUP(B134,EAN,3,0) -> 8435057017237 | H134: 3 x 100 ml | I134: 12 | J134: =D134/I134 -> 0 | K134: ='RESUMEN PEDIDO'!$C$29 -> 0 | L134: ='RESUMEN PEDIDO'!$C$30 -> 0 | M134: =(D134*(E134-(E134*K134)))-(D134*(E134-(E134*K134)))*L134 -> 0
B135: 513102 | C135: KINESSENCES COLOR 3.0 | E135: 36.9 | F135: 40.6 | G135: =VLOOKUP(B135,EAN,3,0) -> 8435057017251 | H135: 3 x 100 ml | I135: 12 | J135: =D135/I135 -> 0 | K135: ='RESUMEN PEDIDO'!$C$29 -> 0 | L135: ='RESUMEN PEDIDO'!$C$30 -> 0 | M135: =(D135*(E135-(E135*K135)))-(D135*(E135-(E135*K135)))*L135 -> 0
B136: 513103 | C136: KINESSENCES COLOR 4.0 | E136: 36.9 | F136: 40.6 | G136: =VLOOKUP(B136,EAN,3,0) -> 8435057017268 | H136: 3 x 100 ml | I136: 12 | J136: =D136/I136 -> 0 | K136: ='RESUMEN PEDIDO'!$C$29 -> 0 | L136: ='RESUMEN PEDIDO'!$C$30 -> 0 | M136: =(D136*(E136-(E136*K136)))-(D136*(E136-(E136*K136)))*L136 -> 0
B137: 513104 | C137: KINESSENCES COLOR 5.0 | E137: 36.9 | F137: 40.6 | G137: =VLOOKUP(B137,EAN,3,0) -> 8435057017275 | H137: 3 x 100 ml | I137: 12 | J137: =D137/I137 -> 0 | K137: ='RESUMEN PEDIDO'!$C$29 -> 0 | L137: ='RESUMEN PEDIDO'!$C$30 -> 0 | M137: =(D137*(E137-(E137*K137)))-(D137*(E137-(E137*K137)))*L137 -> 0
B138: 513105 | C138: KINESSENCES COLOR 6.0 | E138: 36.9 | F138: 40.6 | G138: =VLOOKUP(B138,EAN,3,0) -> 8435057017282 | H138: 3 x 100 ml | I138: 12 | J138: =D138/I138 -> 0 | K138: ='RESUMEN PEDIDO'!$C$29 -> 0 | L138: ='RESUMEN PEDIDO'!$C$30 -> 0 | M138: =(D138*(E138-(E138*K138)))-(D138*(E138-(E138*K138)))*L138 -> 0
B139: 513106 | C139: KINESSENCES COLOR 7.0 | E139: 36.9 | F139: 40.6 | G139: =VLOOKUP(B139,EAN,3,0) -> 8435057017299 | H139: 3 x 100 ml | I139: 12 | J139: =D139/I139 -> 0 | K139: ='RESUMEN PEDIDO'!$C$29 -> 0 | L139: ='RESUMEN PEDIDO'!$C$30 -> 0 | M139: =(D139*(E139-(E139*K139)))-(D139*(E139-(E139*K139)))*L139 -> 0
B140: 513107 | C140: KINESSENCES COLOR 8.0 | E140: 36.9 | F140: 40.6 | G140: =VLOOKUP(B140,EAN,3,0) -> 8435057017305 | H140: 3 x 100 ml | I140: 12 | J140: =D140/I140 -> 0 | K140: ='RESUMEN PEDIDO'!$C$29 -> 0 | L140: ='RESUMEN PEDIDO'!$C$30 -> 0 | M140: =(D140*(E140-(E140*K140)))-(D140*(E140-(E140*K140)))*L140 -> 0
B141: 513108 | C141: KINESSENCES COLOR 9.0 | E141: 36.9 | F141: 40.6 | G141: =VLOOKUP(B141,EAN,3,0) -> 8435057017312 | H141: 3 x 100 ml | I141: 12 | J141: =D141/I141 -> 0 | K141: ='RESUMEN PEDIDO'!$C$29 -> 0 | L141: ='RESUMEN PEDIDO'!$C$30 -> 0 | M141: =(D141*(E141-(E141*K141)))-(D141*(E141-(E141*K141)))*L141 -> 0
B142: 513109 | C142: KINESSENCES COLOR 10.0 | E142: 36.9 | F142: 40.6 | G142: =VLOOKUP(B142,EAN,3,0) -> 8435057017329 | H142: 3 x 100 ml | I142: 12 | J142: =D142/I142 -> 0 | K142: ='RESUMEN PEDIDO'!$C$29 -> 0 | L142: ='RESUMEN PEDIDO'!$C$30 -> 0 | M142: =(D142*(E142-(E142*K142)))-(D142*(E142-(E142*K142)))*L142 -> 0
B143: 513110 | C143: KINESSENCES COLOR 6.02 | E143: 36.9 | F143: 40.6 | G143: =VLOOKUP(B143,EAN,3,0) -> 8435057017336 | H143: 3 x 100 ml | I143: 12 | J143: =D143/I143 -> 0 | K143: ='RESUMEN PEDIDO'!$C$29 -> 0 | L143: ='RESUMEN PEDIDO'!$C$30 -> 0 | M143: =(D143*(E143-(E143*K143)))-(D143*(E143-(E143*K143)))*L143 -> 0
B144: 513111 | C144: KINESSENCES COLOR 7.02 | E144: 36.9 | F144: 40.6 | G144: =VLOOKUP(B144,EAN,3,0) -> 8435057017343 | H144: 3 x 100 ml | I144: 12 | J144: =D144/I144 -> 0 | K144: ='RESUMEN PEDIDO'!$C$29 -> 0 | L144: ='RESUMEN PEDIDO'!$C$30 -> 0 | M144: =(D144*(E144-(E144*K144)))-(D144*(E144-(E144*K144)))*L144 -> 0
B145: 513112 | C145: KINESSENCES COLOR 8.02 | E145: 36.9 | F145: 40.6 | G145: =VLOOKUP(B145,EAN,3,0) -> 8435057017350 | H145: 3 x 100 ml | I145: 12 | J145: =D145/I145 -> 0 | K145: ='RESUMEN PEDIDO'!$C$29 -> 0 | L145: ='RESUMEN PEDIDO'!$C$30 -> 0 | M145: =(D145*(E145-(E145*K145)))-(D145*(E145-(E145*K145)))*L145 -> 0
... B200: 513167 | C200: KINESSENCES COLOR 6.77 | E200: 36.9 | F200: 40.6 | G200: =VLOOKUP(B200,EAN,3,0) -> 8435057017893 | H200: 3 x 100 ml | I200: 12 | J200: =D200/I200 -> 0 | K200: ='RESUMEN PEDIDO'!$C$29 -> 0 | L200: ='RESUMEN PEDIDO'!$C$30 -> 0 | M200: =(D200*(E200-(E200*K200)))-(D200*(E200-(E200*K200)))*L200 -> 0
B201: 513186 | C201: KINESSENCES COLOR LILAC | E201: 36.9 | F201: 40.6 | G201: 8435057019200 | H201: 3 x 100 ml | I201: 12 | J201: =D201/I201 -> 0 | K201: ='RESUMEN PEDIDO'!$C$29 -> 0 | L201: ='RESUMEN PEDIDO'!$C$30 -> 0 | M201: =(D201*(E201-(E201*K201)))-(D201*(E201-(E201*K201)))*L201 -> 0
B202: 513187 | C202: KINESSENCES COLOR STEEL | E202: 36.9 | F202: 40.6 | G202: 8435057019217 | H202: 3 x 100 ml | I202: 12 | J202: =D202/I202 -> 0 | K202: ='RESUMEN PEDIDO'!$C$29 -> 0 | L202: ='RESUMEN PEDIDO'!$C$30 -> 0 | M202: =(D202*(E202-(E202*K202)))-(D202*(E202-(E202*K202)))*L202 -> 0
B203: KINGLOSS COLOR / COLORACIÓN | D203: =SUM(D204:D222) -> 0 | I203: 36 | J203: =D203/I203 -> 0
B204: 560001 | C204: KINGLOSS COLOR 03.0 | E204: 9.2 | F204: 10.1 | G204: 8435057018654 | H204: 50 ml | I204: 12 | J204: =D204/I204 -> 0 | K204: ='RESUMEN PEDIDO'!$C$29 -> 0 | L204: ='RESUMEN PEDIDO'!$C$30 -> 0 | M204: =(D204*(E204-(E204*K204)))-(D204*(E204-(E204*K204)))*L204 -> 0
B205: 560002 | C205: KINGLOSS COLOR 05.0 | E205: 9.2 | F205: 10.1 | G205: 8435057018661 | H205: 50 ml | I205: 12 | J205: =D205/I205 -> 0 | K205: ='RESUMEN PEDIDO'!$C$29 -> 0 | L205: ='RESUMEN PEDIDO'!$C$30 -> 0 | M205: =(D205*(E205-(E205*K205)))-(D205*(E205-(E205*K205)))*L205 -> 0
B206: 560003 | C206: KINGLOSS COLOR 07.0 | E206: 9.2 | F206: 10.1 | G206: 8435057018678 | H206: 50 ml | I206: 12 | J206: =D206/I206 -> 0 | K206: ='RESUMEN PEDIDO'!$C$29 -> 0 | L206: ='RESUMEN PEDIDO'!$C$30 -> 0 | M206: =(D206*(E206-(E206*K206)))-(D206*(E206-(E206*K206)))*L206 -> 0
B207: 560004 | C207: KINGLOSS COLOR 06.1 | E207: 9.2 | F207: 10.1 | G207: 8435057018685 | H207: 50 ml | I207: 12 | J207: =D207/I207 -> 0 | K207: ='RESUMEN PEDIDO'!$C$29 -> 0 | L207: ='RESUMEN PEDIDO'!$C$30 -> 0 | M207: =(D207*(E207-(E207*K207)))-(D207*(E207-(E207*K207)))*L207 -> 0
B208: 560005 | C208: KINGLOSS COLOR 08.1 | E208: 9.2 | F208: 10.1 | G208: 8435057018692 | H208: 50 ml | I208: 12 | J208: =D208/I208 -> 0 | K208: ='RESUMEN PEDIDO'!$C$29 -> 0 | L208: ='RESUMEN PEDIDO'!$C$30 -> 0 | M208: =(D208*(E208-(E208*K208)))-(D208*(E208-(E208*K208)))*L208 -> 0
B209: 560006 | C209: KINGLOSS COLOR 07.11 | E209: 9.2 | F209: 10.1 | G209: 8435057018708 | H209: 50 ml | I209: 12 | J209: =D209/I209 -> 0 | K209: ='RESUMEN PEDIDO'!$C$29 -> 0 | L209: ='RESUMEN PEDIDO'!$C$30 -> 0 | M209: =(D209*(E209-(E209*K209)))-(D209*(E209-(E209*K209)))*L209 -> 0
B210: 560007 | C210: KINGLOSS COLOR 09.12 | E210: 9.2 | F210: 10.1 | G210: 8435057018715 | H210: 50 ml | I210: 12 | J210: =D210/I210 -> 0 | K210: ='RESUMEN PEDIDO'!$C$29 -> 0 | L210: ='RESUMEN PEDIDO'!$C$30 -> 0 | M210: =(D210*(E210-(E210*K210)))-(D210*(E210-(E210*K210)))*L210 -> 0
B211: 560008 | C211: KINGLOSS COLOR 08.13 | E211: 9.2 | F211: 10.1 | G211: 8435057018722 | H211: 50 ml | I211: 12 | J211: =D211/I211 -> 0 | K211: ='RESUMEN PEDIDO'!$C$29 -> 0 | L211: ='RESUMEN PEDIDO'!$C$30 -> 0 | M211: =(D211*(E211-(E211*K211)))-(D211*(E211-(E211*K211)))*L211 -> 0
B212: 560009 | C212: KINGLOSS COLOR 09.19 | E212: 9.2 | F212: 10.1 | G212: 8435057018739 | H212: 50 ml | I212: 12 | J212: =D212/I212 -> 0 | K212: ='RESUMEN PEDIDO'!$C$29 -> 0 | L212: ='RESUMEN PEDIDO'!$C$30 -> 0 | M212: =(D212*(E212-(E212*K212)))-(D212*(E212-(E212*K212)))*L212 -> 0
B213: 560010 | C213: KINGLOSS COLOR 09.2 | E213: 9.2 | F213: 10.1 | G213: 8435057018746 | H213: 50 ml | I213: 12 | J213: =D213/I213 -> 0 | K213: ='RESUMEN PEDIDO'!$C$29 -> 0 | L213: ='RESUMEN PEDIDO'!$C$30 -> 0 | M213: =(D213*(E213-(E213*K213)))-(D213*(E213-(E213*K213)))*L213 -> 0
B214: 560011 | C214: KINGLOSS COLOR 09.32 | E214: 9.2 | F214: 10.1 | G214: 8435057018753 | H214: 50 ml | I214: 12 | J214: =D214/I214 -> 0 | K214: ='RESUMEN PEDIDO'!$C$29 -> 0 | L214: ='RESUMEN PEDIDO'!$C$30 -> 0 | M214: =(D214*(E214-(E214*K214)))-(D214*(E214-(E214*K214)))*L214 -> 0
B215: 560012 | C215: KINGLOSS COLOR 09.37 | E215: 9.2 | F215: 10.1 | G215: 8435057018760 | H215: 50 ml | I215: 12 | J215: =D215/I215 -> 0 | K215: ='RESUMEN PEDIDO'!$C$29 -> 0 | L215: ='RESUMEN PEDIDO'!$C$30 -> 0 | M215: =(D215*(E215-(E215*K215)))-(D215*(E215-(E215*K215)))*L215 -> 0
... B222: 560019 | C222: KINGLOSS COLOR CL00 | E222: 9.2 | F222: 10.1 | G222: 8435057018838 | H222: 50 ml | I222: 12 | J222: =D222/I222 -> 0 | K222: ='RESUMEN PEDIDO'!$C$29 -> 0 | L222: ='RESUMEN PEDIDO'!$C$30 -> 0 | M222: =(D222*(E222-(E222*K222)))-(D222*(E222-(E222*K222)))*L222 -> 0
B223: CANDY COLORS / COLORACIÓN | D223: =SUM(D224:D230) -> 0 | I223: 6 | J223: =SUM(J224:J230) -> 0
B224: 500804 | C224: CANDY COLORS WHITE SUGAR (*) | E224: 16.9 | F224: 18.6 | G224: =VLOOKUP(B224,EAN,3,0) -> 8435057010412 | H224: 200 ml | I224: 6 | J224: =D224/I224 -> 0 | K224: ='RESUMEN PEDIDO'!$C$29 -> 0 | L224: ='RESUMEN PEDIDO'!$C$30 -> 0 | M224: =(D224*(E224-(E224*K224)))-(D224*(E224-(E224*K224)))*L224 -> 0
B225: 500805 | C225: CANDY COLORS RED VELVET (*) | E225: 16.9 | F225: 18.6 | G225: =VLOOKUP(B225,EAN,3,0) -> 8435057010429 | H225: 200 ml | I225: 6 | J225: =D225/I225 -> 0 | K225: ='RESUMEN PEDIDO'!$C$29 -> 0 | L225: ='RESUMEN PEDIDO'!$C$30 -> 0 | M225: =(D225*(E225-(E225*K225)))-(D225*(E225-(E225*K225)))*L225 -> 0
B226: 500806 | C226: CANDY COLORS BLUE GUMMY (*) | E226: 16.9 | F226: 18.6 | G226: =VLOOKUP(B226,EAN,3,0) -> 8435057010436 | H226: 200 ml | I226: 6 | J226: =D226/I226 -> 0 | K226: ='RESUMEN PEDIDO'!$C$29 -> 0 | L226: ='RESUMEN PEDIDO'!$C$30 -> 0 | M226: =(D226*(E226-(E226*K226)))-(D226*(E226-(E226*K226)))*L226 -> 0
B227: 500807 | C227: CANDY COLORS YELLOW MELLOW (*) | E227: 16.9 | F227: 18.6 | G227: =VLOOKUP(B227,EAN,3,0) -> 8435057010443 | H227: 200 ml | I227: 6 | J227: =D227/I227 -> 0 | K227: ='RESUMEN PEDIDO'!$C$29 -> 0 | L227: ='RESUMEN PEDIDO'!$C$30 -> 0 | M227: =(D227*(E227-(E227*K227)))-(D227*(E227-(E227*K227)))*L227 -> 0
B228: 500808 | C228: CANDY COLORS PINK BUBBLEGUM - Temporalmente sin stock | E228: 16.9 | F228: 18.6 | G228: 8435057010436 | H228: 200 ml | I228: 6 | J228: =D228/I228 -> 0 | K228: ='RESUMEN PEDIDO'!$C$29 -> 0 | L228: ='RESUMEN PEDIDO'!$C$30 -> 0 | M228: =(D228*(E228-(E228*K228)))-(D228*(E228-(E228*K228)))*L228 -> 0
B229: 500810 | C229: CANDY COLORS VIOLET CRUMBLE (*) | E229: 16.9 | F229: 18.6 | G229: =VLOOKUP(B229,EAN,3,0) -> 8435057010474 | H229: 200 ml | I229: 6 | J229: =D229/I229 -> 0 | K229: ='RESUMEN PEDIDO'!$C$29 -> 0 | L229: ='RESUMEN PEDIDO'!$C$30 -> 0 | M229: =(D229*(E229-(E229*K229)))-(D229*(E229-(E229*K229)))*L229 -> 0
B230: 500811 | C230: CANDY COLORS SHAMPOO (*) | E230: 11.3 | F230: 12.45 | G230: =VLOOKUP(B230,EAN,3,0) -> 8435057010481 | H230: 200 ml | I230: 6 | J230: =D230/I230 -> 0 | K230: ='RESUMEN PEDIDO'!$C$29 -> 0 | L230: ='RESUMEN PEDIDO'!$C$30 -> 0 | M230: =(D230*(E230-(E230*K230)))-(D230*(E230-(E230*K230)))*L230 -> 0
B231: KINCREM COLOR / COMPLEMENTOS COLORACIÓN | D231: =SUM(D232:D239) -> 0 | J231: =SUM(J233:J239) -> 0
B232: 502121 | C232: KINCREM COLOR ACTIVE CREAM OXIDANT 10 VOL. | E232: 12 | F232: 13.2 | G232: =VLOOKUP(B232,EAN,3,0) -> 8435057016438 | H232: 1.000 ml | I232: 6 | J232: =D232/I232 -> 0 | K232: ='RESUMEN PEDIDO'!$C$29 -> 0 | L232: ='RESUMEN PEDIDO'!$C$30 -> 0 | M232: =(D232*(E232-(E232*K232)))-(D232*(E232-(E232*K232)))*L232 -> 0
B233: 502122 | C233: KINCREM COLOR ACTIVE CREAM OXIDANT 20 VOL. | E233: 12 | F233: 13.2 | G233: =VLOOKUP(B233,EAN,3,0) -> 8435057016445 | H233: 1.000 ml | I233: 6 | J233: =D233/I233 -> 0 | K233: ='RESUMEN PEDIDO'!$C$29 -> 0 | L233: ='RESUMEN PEDIDO'!$C$30 -> 0 | M233: =(D233*(E233-(E233*K233)))-(D233*(E233-(E233*K233)))*L233 -> 0
B234: 502123 | C234: KINCREM COLOR ACTIVE CREAM OXIDANT 30 VOL. | E234: 12 | F234: 13.2 | G234: =VLOOKUP(B234,EAN,3,0) -> 8435057016452 | H234: 1.000 ml | I234: 6 | J234: =D234/I234 -> 0 | K234: ='RESUMEN PEDIDO'!$C$29 -> 0 | L234: ='RESUMEN PEDIDO'!$C$30 -> 0 | M234: =(D234*(E234-(E234*K234)))-(D234*(E234-(E234*K234)))*L234 -> 0
B235: 502124 | C235: KINCREM COLOR ACTIVE CREAM OXIDANT 40 VOL. | E235: 12 | F235: 13.2 | G235: =VLOOKUP(B235,EAN,3,0) -> 8435057016469 | H235: 1.000 ml | I235: 6 | J235: =D235/I235 -> 0 | K235: ='RESUMEN PEDIDO'!$C$29 -> 0 | L235: ='RESUMEN PEDIDO'!$C$30 -> 0 | M235: =(D235*(E235-(E235*K235)))-(D235*(E235-(E235*K235)))*L235 -> 0
B236: 502125 | C236: KINCREM COLOR ACTIVE CREAM OXIDANT 10 VOL. | E236: 3.3 | F236: 3.65 | G236: =VLOOKUP(B236,EAN,3,0) -> 8435057016476 | H236: 100 ml | I236: 36 | J236: =D236/I236 -> 0 | K236: ='RESUMEN PEDIDO'!$C$29 -> 0 | L236: ='RESUMEN PEDIDO'!$C$30 -> 0 | M236: =(D236*(E236-(E236*K236)))-(D236*(E236-(E236*K236)))*L236 -> 0
B237: 502126 | C237: KINCREM COLOR ACTIVE CREAM OXIDANT 20 VOL. | E237: 3.3 | F237: 3.65 | G237: =VLOOKUP(B237,EAN,3,0) -> 8435057016483 | H237: 100 ml | I237: 36 | J237: =D237/I237 -> 0 | K237: ='RESUMEN PEDIDO'!$C$29 -> 0 | L237: ='RESUMEN PEDIDO'!$C$30 -> 0 | M237: =(D237*(E237-(E237*K237)))-(D237*(E237-(E237*K237)))*L237 -> 0
B238: 502127 | C238: KINCREM COLOR ACTIVE CREAM OXIDANT 30 VOL. | E238: 3.3 | F238: 3.65 | G238: =VLOOKUP(B238,EAN,3,0) -> 8435057016490 | H238: 100 ml | I238: 36 | J238: =D238/I238 -> 0 | K238: ='RESUMEN PEDIDO'!$C$29 -> 0 | L238: ='RESUMEN PEDIDO'!$C$30 -> 0 | M238: =(D238*(E238-(E238*K238)))-(D238*(E238-(E238*K238)))*L238 -> 0
B239: 502128 | C239: KINCREM COLOR ACTIVE CREAM OXIDANT 40 VOL. | E239: 3.3 | F239: 3.65 | G239: =VLOOKUP(B239,EAN,3,0) -> 8435057016506 | H239: 100 ml | I239: 36 | J239: =D239/I239 -> 0 | K239: ='RESUMEN PEDIDO'!$C$29 -> 0 | L239: ='RESUMEN PEDIDO'!$C$30 -> 0 | M239: =(D239*(E239-(E239*K239)))-(D239*(E239-(E239*K239)))*L239 -> 0
B240: KINESSENCES COLOR / COMPLEMENTOS COLORACIÓN | D240: =SUM(D241:D248) -> 0 | J240: =SUM(J241:J248) -> 0
B241: 513169 | C241: KINESSENCES COLOR ACTIVE CREAM DEVELOPER 6 VOL. | E241: 12 | F241: 13.2 | G241: =VLOOKUP(B241,EAN,3,0) -> 8435057017909 | H241: 1.000 ml | I241: 6 | J241: =D241/I241 -> 0 | K241: ='RESUMEN PEDIDO'!$C$29 -> 0 | L241: ='RESUMEN PEDIDO'!$C$30 -> 0 | M241: =(D241*(E241-(E241*K241)))-(D241*(E241-(E241*K241)))*L241 -> 0
B242: 513170 | C242: KINESSENCES COLOR ACTIVE CREAM DEVELOPER 12 VOL. | E242: 12 | F242: 13.2 | G242: =VLOOKUP(B242,EAN,3,0) -> 8435057017916 | H242: 1.000 ml | I242: 6 | J242: =D242/I242 -> 0 | K242: ='RESUMEN PEDIDO'!$C$29 -> 0 | L242: ='RESUMEN PEDIDO'!$C$30 -> 0 | M242: =(D242*(E242-(E242*K242)))-(D242*(E242-(E242*K242)))*L242 -> 0
B243: 513171 | C243: KINESSENCES COLOR ACTIVE CREAM DEVELOPER 24 VOL. | E243: 12 | F243: 13.2 | G243: =VLOOKUP(B243,EAN,3,0) -> 8435057017923 | H243: 1.000 ml | I243: 6 | J243: =D243/I243 -> 0 | K243: ='RESUMEN PEDIDO'!$C$29 -> 0 | L243: ='RESUMEN PEDIDO'!$C$30 -> 0 | M243: =(D243*(E243-(E243*K243)))-(D243*(E243-(E243*K243)))*L243 -> 0
B244: 513172 | C244: KINESSENCES COLOR ACTIVE CREAM DEVELOPER 36 VOL. | E244: 12 | F244: 13.2 | G244: =VLOOKUP(B244,EAN,3,0) -> 8435057017930 | H244: 1.000 ml | I244: 6 | J244: =D244/I244 -> 0 | K244: ='RESUMEN PEDIDO'!$C$29 -> 0 | L244: ='RESUMEN PEDIDO'!$C$30 -> 0 | M244: =(D244*(E244-(E244*K244)))-(D244*(E244-(E244*K244)))*L244 -> 0
B245: 513173 | C245: KINESSENCES COLOR ACTIVE CREAM DEVELOPER 6 VOL. | E245: 3.3 | F245: 3.65 | G245: =VLOOKUP(B245,EAN,3,0) -> 8435057017947 | H245: 100 ml | I245: 36 | J245: =D245/I245 -> 0 | K245: ='RESUMEN PEDIDO'!$C$29 -> 0 | L245: ='RESUMEN PEDIDO'!$C$30 -> 0 | M245: =(D245*(E245-(E245*K245)))-(D245*(E245-(E245*K245)))*L245 -> 0
B246: 513174 | C246: KINESSENCES COLOR ACTIVE CREAM DEVELOPER 12 VOL. | E246: 3.3 | F246: 3.65 | G246: =VLOOKUP(B246,EAN,3,0) -> 8435057017954 | H246: 100 ml | I246: 36 | J246: =D246/I246 -> 0 | K246: ='RESUMEN PEDIDO'!$C$29 -> 0 | L246: ='RESUMEN PEDIDO'!$C$30 -> 0 | M246: =(D246*(E246-(E246*K246)))-(D246*(E246-(E246*K246)))*L246 -> 0
B247: 513175 | C247: KINESSENCES COLOR ACTIVE CREAM DEVELOPER 24 VOL. | E247: 3.3 | F247: 3.65 | G247: =VLOOKUP(B247,EAN,3,0) -> 8435057017961 | H247: 100 ml | I247: 36 | J247: =D247/I247 -> 0 | K247: ='RESUMEN PEDIDO'!$C$29 -> 0 | L247: ='RESUMEN PEDIDO'!$C$30 -> 0 | M247: =(D247*(E247-(E247*K247)))-(D247*(E247-(E247*K247)))*L247 -> 0
B248: 513176 | C248: KINESSENCES COLOR ACTIVE CREAM DEVELOPER 36 VOL. | E248: 3.3 | F248: 3.65 | G248: =VLOOKUP(B248,EAN,3,0) -> 8435057017978 | H248: 100 ml | I248: 36 | J248: =D248/I248 -> 0 | K248: ='RESUMEN PEDIDO'!$C$29 -> 0 | L248: ='RESUMEN PEDIDO'!$C$30 -> 0 | M248: =(D248*(E248-(E248*K248)))-(D248*(E248-(E248*K248)))*L248 -> 0
B249: KINGLOSS COLOR / COMPLEMENTOS COLORACIÓN | D249: =SUM(D250:D251) -> 0 | J249: =SUM(J250:J251) -> 0
B250: 560020 | C250: BRUSH & BOTTLE ACTIVE DEVELOPER 5 VOL. | E250: 12 | F250: 13.2 | G250: 8435057018845 | H250: 1.000 ml | I250: 6 | J250: =D250/I250 -> 0 | K250: ='RESUMEN PEDIDO'!$C$29 -> 0 | L250: ='RESUMEN PEDIDO'!$C$30 -> 0 | M250: =(D250*(E250-(E250*K250)))-(D250*(E250-(E250*K250)))*L250 -> 0
B251: 560021 | C251: BRUSH & BOTTLE ACTIVE DEVELOPER 5 VOL. | E251: 3.3 | F251: 3.65 | G251: 8435057018852 | H251: 100 ml | I251: 36 | J251: =D251/I251 -> 0 | K251: ='RESUMEN PEDIDO'!$C$29 -> 0 | L251: ='RESUMEN PEDIDO'!$C$30 -> 0 | M251: =(D251*(E251-(E251*K251)))-(D251*(E251-(E251*K251)))*L251 -> 0
B252: KINMASTER / COMPLEMENTOS COLORACIÓN | D252: =SUM(D253:D259) -> 0 | I252: 6 | J252: =SUM(J253:J259) -> 0
B253: 540056 | C253: KINMASTER EQUILIBRANT SHAMPOO | E253: 31 | F253: 34.1 | G253: =VLOOKUP(B253,EAN,3,0) -> 8435057013871 | H253: 1.000 ml | I253: 6 | J253: =D253/I253 -> 0 | K253: ='RESUMEN PEDIDO'!$C$29 -> 0 | L253: ='RESUMEN PEDIDO'!$C$30 -> 0 | M253: =(D253*(E253-(E253*K253)))-(D253*(E253-(E253*K253)))*L253 -> 0
B254: 540111 | C254: KINMASTER DEEP CLEANSING SHAMPOO | E254: 31 | F254: 34.1 | G254: 8435057020299 | H254: 1.000 ml | I254: 6 | J254: =D254/I254 -> 0 | K254: ='RESUMEN PEDIDO'!$C$29 -> 0 | L254: ='RESUMEN PEDIDO'!$C$30 -> 0 | M254: =(D254*(E254-(E254*K254)))-(D254*(E254-(E254*K254)))*L254 -> 0
B255: 540090 | C255: KINMASTER DEEP CLEANSING SHAMPOO (*) | E255: 12 | F255: 13.2 | G255: 8435057018951 | H255: 250 ml | I255: 6 | J255: =D255/I255 -> 0 | K255: ='RESUMEN PEDIDO'!$C$29 -> 0 | L255: ='RESUMEN PEDIDO'!$C$30 -> 0 | M255: =(D255*(E255-(E255*K255)))-(D255*(E255-(E255*K255)))*L255 -> 0
B256: 540064 | C256: KINMASTER NO YELLOW SHAMPOO | E256: 31 | F256: 34.1 | G256: =VLOOKUP(B256,EAN,3,0) -> 8435057014243 | H256: 1.000 ml | I256: 6 | J256: =D256/I256 -> 0 | K256: ='RESUMEN PEDIDO'!$C$29 -> 0 | L256: ='RESUMEN PEDIDO'!$C$30 -> 0 | M256: =(D256*(E256-(E256*K256)))-(D256*(E256-(E256*K256)))*L256 -> 0
B257: 540080 | C257: KINMASTER NO ORANGE SHAMPOO | E257: 31 | F257: 34.1 | G257: =VLOOKUP(B257,EAN,3,0) -> 8435057015202 | H257: 1.000 ml | I257: 6 | J257: =D257/I257 -> 0 | K257: ='RESUMEN PEDIDO'!$C$29 -> 0 | L257: ='RESUMEN PEDIDO'!$C$30 -> 0 | M257: =(D257*(E257-(E257*K257)))-(D257*(E257-(E257*K257)))*L257 -> 0
B258: 540058 | C258: KINMASTER COLOR CLEANSER | E258: 9.1 | F258: 10 | G258: =VLOOKUP(B258,EAN,3,0) -> 8435057013949 | H258: 75 ml | I258: 6 | J258: =D258/I258 -> 0 | K258: ='RESUMEN PEDIDO'!$C$29 -> 0 | L258: ='RESUMEN PEDIDO'!$C$30 -> 0 | M258: =(D258*(E258-(E258*K258)))-(D258*(E258-(E258*K258)))*L258 -> 0
B259: 540099 | C259: KINMASTER COLOR REMOVER | E259: 18 | F259: 19.8 | G259: 8435057019699 | H259: 2 x 50 ml | I259: 6 | J259: =D259/I259 -> 0 | K259: ='RESUMEN PEDIDO'!$C$29 -> 0 | L259: ='RESUMEN PEDIDO'!$C$30 -> 0 | M259: =(D259*(E259-(E259*K259)))-(D259*(E259-(E259*K259)))*L259 -> 0
B260: KINBLOND / DECOLORACIÓN | D260: =SUM(D261:D266) -> 0 | I260: 6 | J260: =SUM(J261:J266) -> 0
B261: 501201 | C261: KINBLOND 9 ADVANCED LIGHTENING POWDER | E261: 45.5 | F261: 50.05 | G261: 8435057020152 | H261: 500 gr | I261: 6 | J261: =D261/I261 -> 0 | K261: ='RESUMEN PEDIDO'!$C$29 -> 0 | L261: ='RESUMEN PEDIDO'!$C$30 -> 0 | M261: =(D261*(E261-(E261*K261)))-(D261*(E261-(E261*K261)))*L261 -> 0
B262: 501202 | C262: KINBLOND 8 FLEXIBLE LIGHTENING POWDER | E262: 45.5 | F262: 50.05 | G262: 8435057020169 | H262: 500 gr | I262: 6 | J262: =D262/I262 -> 0 | K262: ='RESUMEN PEDIDO'!$C$29 -> 0 | L262: ='RESUMEN PEDIDO'!$C$30 -> 0 | M262: =(D262*(E262-(E262*K262)))-(D262*(E262-(E262*K262)))*L262 -> 0
B263: 501204 | C263: KINBLOND ACTIVE PROTECTIVE OXIDANT | E263: 12 | F263: 13.2 | G263: 8435057020183 | H263: 1.000 ml | I263: 6 | J263: =D263/I263 -> 0 | K263: ='RESUMEN PEDIDO'!$C$29 -> 0 | L263: ='RESUMEN PEDIDO'!$C$30 -> 0 | M263: =(D263*(E263-(E263*K263)))-(D263*(E263-(E263*K263)))*L263 -> 0
B264: 501205 | C264: KINBLOND ACTIVE PROTECTIVE OXIDANT | E264: 3.3 | F264: 3.65 | G264: 8435057020190 | H264: 100 ml | I264: 36 | J264: =D264/I264 -> 0 | K264: ='RESUMEN PEDIDO'!$C$29 -> 0 | L264: ='RESUMEN PEDIDO'!$C$30 -> 0 | M264: =(D264*(E264-(E264*K264)))-(D264*(E264-(E264*K264)))*L264 -> 0
B265: 501206 | C265: PACK SACHETS KINBLOND 9 ADVENCED LIGHTENING POWDER | E265: 63 | F265: 69.3 | G265: 8435057020039 | H265: 10 x 50 gr | I265: 1 | J265: =D265/I265 -> 0 | K265: ='RESUMEN PEDIDO'!$C$29 -> 0 | L265: ='RESUMEN PEDIDO'!$C$30 -> 0 | M265: =(D265*(E265-(E265*K265)))-(D265*(E265-(E265*K265)))*L265 -> 0
B266: 501207 | C266: PACK SACHETS KINBLOND 8 FLEXIBLE LIGHTENING POWDER | E266: 63 | F266: 69.3 | G266: 8435057020053 | H266: 10 x 50 gr | I266: 1 | J266: =D266/I266 -> 0 | K266: ='RESUMEN PEDIDO'!$C$29 -> 0 | L266: ='RESUMEN PEDIDO'!$C$30 -> 0 | M266: =(D266*(E266-(E266*K266)))-(D266*(E266-(E266*K266)))*L266 -> 0
B267: KINSMOOTH / FORMA | D267: =SUM(D268:D270) -> 0 | J267: =SUM(J268:J270) -> 0
B268: 540091 | C268: KINSMOOTH HAIR LAMINATING PROFESSIONAL KIT | E268: 166 | F268: 182.6 | G268: 8435057019453 | H268: pack | I268: 4 | J268: =D268/I268 -> 0 | K268: ='RESUMEN PEDIDO'!$C$29 -> 0 | L268: ='RESUMEN PEDIDO'!$C$30 -> 0 | M268: =(D268*(E268-(E268*K268)))-(D268*(E268-(E268*K268)))*L268 -> 0
B269: 540093 | C269: KINSMOOTH LAMINATING FOAM | E269: 26 | F269: 28.6 | G269: 8435057019477 | H269: 150 ml | I269: 6 | J269: =D269/I269 -> 0 | K269: ='RESUMEN PEDIDO'!$C$29 -> 0 | L269: ='RESUMEN PEDIDO'!$C$30 -> 0 | M269: =(D269*(E269-(E269*K269)))-(D269*(E269-(E269*K269)))*L269 -> 0
B270: 540094 | C270: KINSMOOTH LAMINATING CREAM | E270: 16 | F270: 17.6 | G270: 8435057019484 | H270: 150 ml | I270: 6 | J270: =D270/I270 -> 0 | K270: ='RESUMEN PEDIDO'!$C$29 -> 0 | L270: ='RESUMEN PEDIDO'!$C$30 -> 0 | M270: =(D270*(E270-(E270*K270)))-(D270*(E270-(E270*K270)))*L270 -> 0
...

Sheet PRODUCTO REVENTA
B1: KIN COSMETICS, S.A.U.
B2: HOJA DE PEDIDO DISTRIBUIDOR
B6: PRODUCTO REVENTA
B7: SUBTOTAL PRODUCTO REVENTA | D7: =D9+D15+D20+D63+D81+D90+D99 -> 0 | J7: =J9+J15+J20+J63+J81+J90+J99 -> 0 | M7: =SUBTOTAL(9,M9:M100) -> 0
B8: Ref. | C8: Descripción | D8: Unidades | E8: Precio Tarifa | F8: PVP | G8: Código EAN | H8: Formato | I8: Packing | J8: Cajas | K8: Dto. 1% | L8: Dto. 2% | M8: Subtotal
B9: KINMEN / TRATAMIENTOS | D9: =SUM(D10:D14) -> 0 | J9: =SUM(J10:J14) -> 0
B10: 550077 | C10: KINMEN FORCE SHAMPOO | E10: 13 | F10: 14.3 | G10: =VLOOKUP(B10,EAN,3,0) -> 8435057016537 | H10: 300 ml | I10: 6 | J10: =D10/I10 -> 0 | K10: ='RESUMEN PEDIDO'!$C$29 -> 0 | L10: ='RESUMEN PEDIDO'!$C$30 -> 0 | M10: =(D10*(E10-(E10*K10)))-(D10*(E10-(E10*K10)))*L10 -> 0
B11: 550076 | C11: KINMEN SILVER SHAMPOO | E11: 13 | F11: 14.3 | G11: =VLOOKUP(B11,EAN,3,0) -> 8435057016520 | H11: 300 ml | I11: 6 | J11: =D11/I11 -> 0 | K11: ='RESUMEN PEDIDO'!$C$29 -> 0 | L11: ='RESUMEN PEDIDO'!$C$30 -> 0 | M11: =(D11*(E11-(E11*K11)))-(D11*(E11-(E11*K11)))*L11 -> 0
B12: 550075 | C12: KINMEN 3-IN-1 SHAMPOO | E12: 13 | F12: 14.3 | G12: =VLOOKUP(B12,EAN,3,0) -> 8435057016513 | H12: 300 ml | I12: 6 | J12: =D12/I12 -> 0 | K12: ='RESUMEN PEDIDO'!$C$29 -> 0 | L12: ='RESUMEN PEDIDO'!$C$30 -> 0 | M12: =(D12*(E12-(E12*K12)))-(D12*(E12-(E12*K12)))*L12 -> 0
B13: 550040 | C13: KINMEN FORCE TONIC | E13: 18 | F13: 19.8 | G13: =VLOOKUP(B13,EAN,3,0) -> 8435057013536 | H13: 125 ml | I13: 6 | J13: =D13/I13 -> 0 | K13: ='RESUMEN PEDIDO'!$C$29 -> 0 | L13: ='RESUMEN PEDIDO'!$C$30 -> 0 | M13: =(D13*(E13-(E13*K13)))-(D13*(E13-(E13*K13)))*L13 -> 0
B14: 550092 | C14: KINMEN BEARD CREAM | E14: 9 | F14: 9.9 | G14: 8435057020572 | H14: 50 ml | I14: 12 | J14: =D14/I14 -> 0 | K14: ='RESUMEN PEDIDO'!$C$29 -> 0 | L14: ='RESUMEN PEDIDO'!$C$30 -> 0 | M14: =(D14*(E14-(E14*K14)))-(D14*(E14-(E14*K14)))*L14 -> 0
B15: KINMEN / STYLING | D15: =SUM(D16:D19) -> 0 | J15: =SUM(J16:J19) -> 0
B16: 550078 | C16: KINMEN HAIR MATTE CLAY | E16: 15.5 | F16: 17.05 | G16: =VLOOKUP(B16,EAN,3,0) -> 8435057016544 | H16: 100 ml | I16: 6 | J16: =D16/I16 -> 0 | K16: ='RESUMEN PEDIDO'!$C$29 -> 0 | L16: ='RESUMEN PEDIDO'!$C$30 -> 0 | M16: =(D16*(E16-(E16*K16)))-(D16*(E16-(E16*K16)))*L16 -> 0
B17: 550079 | C17: KINMEN HAIR FIBER PASTE | E17: 15.5 | F17: 17.05 | G17: =VLOOKUP(B17,EAN,3,0) -> 8435057016551 | H17: 100 ml | I17: 6 | J17: =D17/I17 -> 0 | K17: ='RESUMEN PEDIDO'!$C$29 -> 0 | L17: ='RESUMEN PEDIDO'!$C$30 -> 0 | M17: =(D17*(E17-(E17*K17)))-(D17*(E17-(E17*K17)))*L17 -> 0
B18: 550084 | C18: KINMEN HAIR WET GEL | E18: 12 | F18: 13.2 | G18: =VLOOKUP(B18,EAN,3,0) -> 8435057016605 | H18: 150 ml | I18: 6 | J18: =D18/I18 -> 0 | K18: ='RESUMEN PEDIDO'!$C$29 -> 0 | L18: ='RESUMEN PEDIDO'!$C$30 -> 0 | M18: =(D18*(E18-(E18*K18)))-(D18*(E18-(E18*K18)))*L18 -> 0
B19: 550085 | C19: KINMEN POWER GEL | E19: 16.5 | F19: 18.15 | G19: =VLOOKUP(B19,EAN,3,0) -> 8435057016612 | H19: 150 ml | I19: 6 | J19: =D19/I19 -> 0 | K19: ='RESUMEN PEDIDO'!$C$29 -> 0 | L19: ='RESUMEN PEDIDO'!$C$30 -> 0 | M19: =(D19*(E19-(E19*K19)))-(D19*(E19-(E19*K19)))*L19 -> 0
B20: KINACTIF / TRATAMIENTOS | D20: =SUM(D21:D62) -> 0 | J20: =SUM(J21:J62) -> 0
B21: 511002 | C21: KINACTIF (Nº1 NUTRITION) DAILY MOISTURIZING SHAMPOO | E21: 14 | F21: 15.4 | G21: 8435057018012 | H21: 300 ml | I21: 6 | J21: =D21/I21 -> 0 | K21: ='RESUMEN PEDIDO'!$C$29 -> 0 | L21: ='RESUMEN PEDIDO'!$C$30 -> 0 | M21: =(D21*(E21-(E21*K21)))-(D21*(E21-(E21*K21)))*L21 -> 0
B22: 511004 | C22: KINACTIF (Nº1 NUTRITION) RICH NOURISHING SHAMPOO | E22: 14 | F22: 15.4 | G22: 8435057018036 | H22: 300 ml | I22: 6 | J22: =D22/I22 -> 0 | K22: ='RESUMEN PEDIDO'!$C$29 -> 0 | L22: ='RESUMEN PEDIDO'!$C$30 -> 0 | M22: =(D22*(E22-(E22*K22)))-(D22*(E22-(E22*K22)))*L22 -> 0
B23: 511006 | C23: KINACTIF (Nº1 NUTRITION) NOURISHING 2-IN-1 MASK | E23: 17.5 | F23: 19.25 | G23: 8435057018050 | H23: 200 ml | I23: 6 | J23: =D23/I23 -> 0 | K23: ='RESUMEN PEDIDO'!$C$29 -> 0 | L23: ='RESUMEN PEDIDO'!$C$30 -> 0 | M23: =(D23*(E23-(E23*K23)))-(D23*(E23-(E23*K23)))*L23 -> 0
B24: 511009 | C24: KINACTIF (Nª1 NUTRITION) MOISTURIZING CONDITIONING SPRAY | E24: 13.6 | F24: 14.95 | G24: 8435057018081 | H24: 200 ml | I24: 6 | J24: =D24/I24 -> 0 | K24: ='RESUMEN PEDIDO'!$C$29 -> 0 | L24: ='RESUMEN PEDIDO'!$C$30 -> 0 | M24: =(D24*(E24-(E24*K24)))-(D24*(E24-(E24*K24)))*L24 -> 0
B25: 511010 | C25: KINACTIF (Nª1 NUTRITION) NOURISHING MELTING EXTRACT | E25: 16.4 | F25: 18.05 | G25: 8435057018098 | H25: 150 ml | I25: 6 | J25: =D25/I25 -> 0 | K25: ='RESUMEN PEDIDO'!$C$29 -> 0 | L25: ='RESUMEN PEDIDO'!$C$30 -> 0 | M25: =(D25*(E25-(E25*K25)))-(D25*(E25-(E25*K25)))*L25 -> 0
B26: 511149 | C26: KINACTIF (Nº1 NUTRITION) MOISTURIZING PACK (SHAMPOO + MASK + M. SPRAY) | E26: 45.1 | F26: 49.6 | G26: 8435057020411 | H26: 300 ml + 200 ml + 200 ml | I26: 6 | J26: =D26/I26 -> 0 | K26: ='RESUMEN PEDIDO'!$C$29 -> 0 | L26: ='RESUMEN PEDIDO'!$C$30 -> 0 | M26: =(D26*(E26-(E26*K26)))-(D26*(E26-(E26*K26)))*L26 -> 0
B27: 511150 | C27: KINACTIF (Nº1 NUTRITION) NOURISHING PACK (SHAMPOO + MASK + M. EXTRACT) | E27: 47.9 | F27: 52.7 | G27: 8435057020428 | H27: 300 ml + 200 ml + 150 ml | I27: 6 | J27: =D27/I27 -> 0 | K27: ='RESUMEN PEDIDO'!$C$29 -> 0 | L27: ='RESUMEN PEDIDO'!$C$30 -> 0 | M27: =(D27*(E27-(E27*K27)))-(D27*(E27-(E27*K27)))*L27 -> 0
B28: 511011 | C28: KINACTIF (Nº2 REPAIR) RICH RECONSTRUCTING SHAMPOO | E28: 14 | F28: 15.4 | G28: 8435057018104 | H28: 300 ml | I28: 6 | J28: =D28/I28 -> 0 | K28: ='RESUMEN PEDIDO'!$C$29 -> 0 | L28: ='RESUMEN PEDIDO'!$C$30 -> 0 | M28: =(D28*(E28-(E28*K28)))-(D28*(E28-(E28*K28)))*L28 -> 0
B29: 511013 | C29: KINACTIF (Nº2 REPAIR) RECONSTRUCTING 2-IN-1 MASK | E29: 17.5 | F29: 19.25 | G29: 8435057018128 | H29: 200 ml | I29: 6 | J29: =D29/I29 -> 0 | K29: ='RESUMEN PEDIDO'!$C$29 -> 0 | L29: ='RESUMEN PEDIDO'!$C$30 -> 0 | M29: =(D29*(E29-(E29*K29)))-(D29*(E29-(E29*K29)))*L29 -> 0
B30: 511016 | C30: KINACTIF (Nº2 REPAIR) RECONSTRUCTING MELTING EXTRACT | E30: 16.4 | F30: 18.05 | G30: 8435057018159 | H30: 150 ml | I30: 6 | J30: =D30/I30 -> 0 | K30: ='RESUMEN PEDIDO'!$C$29 -> 0 | L30: ='RESUMEN PEDIDO'!$C$30 -> 0 | M30: =(D30*(E30-(E30*K30)))-(D30*(E30-(E30*K30)))*L30 -> 0
B31: 511151 | C31: KINACTIF (Nº2 REPAIR) PACK (SHAMPOO + MASK + M. EXTRACT) | E31: 47.9 | F31: 52.7 | G31: 8435057020435 | H31: 300 ml + 200 ml + 150 ml | I31: 6 | J31: =D31/I31 -> 0 | K31: ='RESUMEN PEDIDO'!$C$29 -> 0 | L31: ='RESUMEN PEDIDO'!$C$30 -> 0 | M31: =(D31*(E31-(E31*K31)))-(D31*(E31-(E31*K31)))*L31 -> 0
B32: 511017 | C32: KINACTIF (Nº3 VOLUME) MILD EXPANDING SHAMPOO | E32: 14 | F32: 15.4 | G32: 8435057018166 | H32: 300 ml | I32: 6 | J32: =D32/I32 -> 0 | K32: ='RESUMEN PEDIDO'!$C$29 -> 0 | L32: ='RESUMEN PEDIDO'!$C$30 -> 0 | M32: =(D32*(E32-(E32*K32)))-(D32*(E32-(E32*K32)))*L32 -> 0
B33: 511019 | C33: KINACTIF (Nº3 VOLUME) EXPANDING 2-IN-1 MASK | E33: 17.5 | F33: 19.25 | G33: 8435057018180 | H33: 200 ml | I33: 6 | J33: =D33/I33 -> 0 | K33: ='RESUMEN PEDIDO'!$C$29 -> 0 | L33: ='RESUMEN PEDIDO'!$C$30 -> 0 | M33: =(D33*(E33-(E33*K33)))-(D33*(E33-(E33*K33)))*L33 -> 0
B34: 511020 | C34: KINACTIF (Nº3 VOLUME) EXPANDING ROOT FOAM | E34: 15.3 | F34: 16.85 | G34: 8435057018197 | H34: 150 ml | I34: 6 | J34: =D34/I34 -> 0 | K34: ='RESUMEN PEDIDO'!$C$29 -> 0 | L34: ='RESUMEN PEDIDO'!$C$30 -> 0 | M34: =(D34*(E34-(E34*K34)))-(D34*(E34-(E34*K34)))*L34 -> 0
B35: 511152 | C35: KINACTIF (Nº3 VOLUME) PACK (SHAMPOO + MASK + R. FOAM) | E35: 46.8 | F35: 51.5 | G35: 8435057020442 | H35: 300 ml + 200 ml + 150 ml | I35: 6 | J35: =D35/I35 -> 0 | K35: ='RESUMEN PEDIDO'!$C$29 -> 0 | L35: ='RESUMEN PEDIDO'!$C$30 -> 0 | M35: =(D35*(E35-(E35*K35)))-(D35*(E35-(E35*K35)))*L35 -> 0
B36: 511047 | C36: KINACTIF (Nº4 COLOR) COLOR PROTECTING SHAMPOO | E36: 14 | F36: 15.4 | G36: 8435057019019 | H36: 300 ml | I36: 6 | J36: =D36/I36 -> 0 | K36: ='RESUMEN PEDIDO'!$C$29 -> 0 | L36: ='RESUMEN PEDIDO'!$C$30 -> 0 | M36: =(D36*(E36-(E36*K36)))-(D36*(E36-(E36*K36)))*L36 -> 0
B37: 511051 | C37: KINACTIF (Nº4 COLOR) COLOR PROTECTING 2-IN-1 MASK | E37: 17.5 | F37: 19.25 | G37: 8435057019057 | H37: 200 ml | I37: 6 | J37: =D37/I37 -> 0 | K37: ='RESUMEN PEDIDO'!$C$29 -> 0 | L37: ='RESUMEN PEDIDO'!$C$30 -> 0 | M37: =(D37*(E37-(E37*K37)))-(D37*(E37-(E37*K37)))*L37 -> 0
B38: 511055 | C38: KINACTIF (Nº4 COLOR) COLOR PROTECTING MELTING EXTRACT | E38: 16.4 | F38: 18.05 | G38: 8435057019095 | H38: 150 ml | I38: 6 | J38: =D38/I38 -> 0 | K38: ='RESUMEN PEDIDO'!$C$29 -> 0 | L38: ='RESUMEN PEDIDO'!$C$30 -> 0 | M38: =(D38*(E38-(E38*K38)))-(D38*(E38-(E38*K38)))*L38 -> 0
B39: 511153 | C39: KINACTIF (Nº4 COLOR) PACK (SHAMPOO + MASK + M. EXTRACT) | E39: 47.9 | F39: 52.7 | G39: 8435057020459 | H39: 300 ml + 200 ml + 150 ml | I39: 6 | J39: =D39/I39 -> 0 | K39: ='RESUMEN PEDIDO'!$C$29 -> 0 | L39: ='RESUMEN PEDIDO'!$C$30 -> 0 | M39: =(D39*(E39-(E39*K39)))-(D39*(E39-(E39*K39)))*L39 -> 0
B40: 511049 | C40: KINACTIF (Nº5 BLONDE) ANTI-BRASS BLONDE SHAMPOO | E40: 14 | F40: 15.4 | G40: 8435057019033 | H40: 300 ml | I40: 6 | J40: =D40/I40 -> 0 | K40: ='RESUMEN PEDIDO'!$C$29 -> 0 | L40: ='RESUMEN PEDIDO'!$C$30 -> 0 | M40: =(D40*(E40-(E40*K40)))-(D40*(E40-(E40*K40)))*L40 -> 0
B41: 511053 | C41: KINACTIF (Nº5 BLONDE) ANTI-BRASS BLONDE MASK | E41: 17.5 | F41: 19.25 | G41: 8435057019071 | H41: 200 ml | I41: 6 | J41: =D41/I41 -> 0 | K41: ='RESUMEN PEDIDO'!$C$29 -> 0 | L41: ='RESUMEN PEDIDO'!$C$30 -> 0 | M41: =(D41*(E41-(E41*K41)))-(D41*(E41-(E41*K41)))*L41 -> 0
B42: 511021 | C42: KINACTIF (Nº6 SUNCARE) AFTERSUN SHAMPOO & SHOWER GEL | E42: 14 | F42: 15.4 | G42: 8435057018203 | H42: 300 ml | I42: 6 | J42: =D42/I42 -> 0 | K42: ='RESUMEN PEDIDO'!$C$29 -> 0 | L42: ='RESUMEN PEDIDO'!$C$30 -> 0 | M42: =(D42*(E42-(E42*K42)))-(D42*(E42-(E42*K42)))*L42 -> 0
B43: 511022 | C43: KINACTIF (Nº6 SUNCARE) AFTERSUN 2-IN-1 MASK | E43: 17 | F43: 18.7 | G43: 8435057018210 | H43: 200 ml | I43: 6 | J43: =D43/I43 -> 0 | K43: ='RESUMEN PEDIDO'!$C$29 -> 0 | L43: ='RESUMEN PEDIDO'!$C$30 -> 0 | M43: =(D43*(E43-(E43*K43)))-(D43*(E43-(E43*K43)))*L43 -> 0
B44: 511023 | C44: KINACTIF (Nº6 SUNCARE) SUN PROTECTIVE MILK | E44: 18.5 | F44: 20.35 | G44: 8435057018227 | H44: 200 ml | I44: 6 | J44: =D44/I44 -> 0 | K44: ='RESUMEN PEDIDO'!$C$29 -> 0 | L44: ='RESUMEN PEDIDO'!$C$30 -> 0 | M44: =(D44*(E44-(E44*K44)))-(D44*(E44-(E44*K44)))*L44 -> 0
B45: 511081 | C45: KINACTIF (Nº7 CONTROL) CURL ENHANCING SHAMPOO | E45: 14 | F45: 15.4 | G45: 8435057019514 | H45: 300 ml | I45: 6 | J45: =D45/I45 -> 0 | K45: ='RESUMEN PEDIDO'!$C$29 -> 0 | L45: ='RESUMEN PEDIDO'!$C$30 -> 0 | M45: =(D45*(E45-(E45*K45)))-(D45*(E45-(E45*K45)))*L45 -> 0
B46: 511086 | C46: KINACTIF (Nº7 CONTROL) CURL ENHANCING 2-IN-1 MASK | E46: 17.5 | F46: 19.25 | G46: 8435057019569 | H46: 200 ml | I46: 6 | J46: =D46/I46 -> 0 | K46: ='RESUMEN PEDIDO'!$C$29 -> 0 | L46: ='RESUMEN PEDIDO'!$C$30 -> 0 | M46: =(D46*(E46-(E46*K46)))-(D46*(E46-(E46*K46)))*L46 -> 0
... B62: 511144 | C62: KINACTIF (Nº8 SCALP) MULTIVITAMIN SCALP SERUM | E62: 17.5 | F62: 19.25 | G62: 8435057020275 | H62: 75 ml | I62: 6 | J62: =D62/I62 -> 0 | K62: ='RESUMEN PEDIDO'!$C$29 -> 0 | L62: ='RESUMEN PEDIDO'!$C$30 -> 0 | M62: =(D62*(E62-(E62*K62)))-(D62*(E62-(E62*K62)))*L62 -> 0
B63: KINESSENCES / TRATAMIENTOS | D63: =SUM(D64:D80) -> 0 | J63: =SUM(J64:J80) -> 0
B64: 513001 | C64: KINESSENCES NOURISH GENTLE SHAMPOO | E64: 17 | F64: 18.7 | G64: =VLOOKUP(B64,EAN,3,0) -> 8435057017039 | H64: 300 ml | I64: 6 | J64: =D64/I64 -> 0 | K64: ='RESUMEN PEDIDO'!$C$29 -> 0 | L64: ='RESUMEN PEDIDO'!$C$30 -> 0 | M64: =(D64*(E64-(E64*K64)))-(D64*(E64-(E64*K64)))*L64 -> 0
B65: 513003 | C65: KINESSENCES NOURISH INTENSE MASK | E65: 17.5 | F65: 19.25 | G65: =VLOOKUP(B65,EAN,3,0) -> 8435057017053 | H65: 200 ml | I65: 6 | J65: =D65/I65 -> 0 | K65: ='RESUMEN PEDIDO'!$C$29 -> 0 | L65: ='RESUMEN PEDIDO'!$C$30 -> 0 | M65: =(D65*(E65-(E65*K65)))-(D65*(E65-(E65*K65)))*L65 -> 0
B66: 513005 | C66: KINESSENCES NOURISH OIL | E66: 8.9 | F66: 9.8 | G66: =VLOOKUP(B66,EAN,3,0) -> 8435057017077 | H66: 30 ml | I66: 12 | J66: =D66/I66 -> 0 | K66: ='RESUMEN PEDIDO'!$C$29 -> 0 | L66: ='RESUMEN PEDIDO'!$C$30 -> 0 | M66: =(D66*(E66-(E66*K66)))-(D66*(E66-(E66*K66)))*L66 -> 0
B67: 513006 | C67: KINESSENCES NOURISH OIL CREAM | E67: 9.9 | F67: 10.9 | G67: =VLOOKUP(B67,EAN,3,0) -> 8435057017084 | H67: 50 ml | I67: 12 | J67: =D67/I67 -> 0 | K67: ='RESUMEN PEDIDO'!$C$29 -> 0 | L67: ='RESUMEN PEDIDO'!$C$30 -> 0 | M67: =(D67*(E67-(E67*K67)))-(D67*(E67-(E67*K67)))*L67 -> 0
B68: 513007 | C68: KINESSENCES ANTIOX GENTLE SHAMPOO | E68: 17 | F68: 18.7 | G68: =VLOOKUP(B68,EAN,3,0) -> 8435057017091 | H68: 300 ml | I68: 6 | J68: =D68/I68 -> 0 | K68: ='RESUMEN PEDIDO'!$C$29 -> 0 | L68: ='RESUMEN PEDIDO'!$C$30 -> 0 | M68: =(D68*(E68-(E68*K68)))-(D68*(E68-(E68*K68)))*L68 -> 0
B69: 513009 | C69: KINESSENCES ANTIOX INTENSE MASK | E69: 17.5 | F69: 19.25 | G69: =VLOOKUP(B69,EAN,3,0) -> 8435057017114 | H69: 200 ml | I69: 6 | J69: =D69/I69 -> 0 | K69: ='RESUMEN PEDIDO'!$C$29 -> 0 | L69: ='RESUMEN PEDIDO'!$C$30 -> 0 | M69: =(D69*(E69-(E69*K69)))-(D69*(E69-(E69*K69)))*L69 -> 0
B70: 513011 | C70: KINESSENCES ANTIOX SMOOTHIE | E70: 9.9 | F70: 10.9 | G70: =VLOOKUP(B70,EAN,3,0) -> 8435057017138 | H70: 50 ml | I70: 6 | J70: =D70/I70 -> 0 | K70: ='RESUMEN PEDIDO'!$C$29 -> 0 | L70: ='RESUMEN PEDIDO'!$C$30 -> 0 | M70: =(D70*(E70-(E70*K70)))-(D70*(E70-(E70*K70)))*L70 -> 0
B71: 513012 | C71: KINESSENCES ANTIOX NECTAR | E71: 18 | F71: 19.8 | G71: =VLOOKUP(B71,EAN,3,0) -> 8435057017145 | H71: 150 ml | I71: 6 | J71: =D71/I71 -> 0 | K71: ='RESUMEN PEDIDO'!$C$29 -> 0 | L71: ='RESUMEN PEDIDO'!$C$30 -> 0 | M71: =(D71*(E71-(E71*K71)))-(D71*(E71-(E71*K71)))*L71 -> 0
B72: 513013 | C72: KINESSENCES RESTORE GENTLE SHAMPOO | E72: 17 | F72: 18.7 | G72: =VLOOKUP(B72,EAN,3,0) -> 8435057017152 | H72: 300 ml | I72: 6 | J72: =D72/I72 -> 0 | K72: ='RESUMEN PEDIDO'!$C$29 -> 0 | L72: ='RESUMEN PEDIDO'!$C$30 -> 0 | M72: =(D72*(E72-(E72*K72)))-(D72*(E72-(E72*K72)))*L72 -> 0
B73: 513015 | C73: KINESSENCES RESTORE INTENSE MASK | E73: 17.5 | F73: 19.25 | G73: =VLOOKUP(B73,EAN,3,0) -> 8435057017176 | H73: 200 ml | I73: 6 | J73: =D73/I73 -> 0 | K73: ='RESUMEN PEDIDO'!$C$29 -> 0 | L73: ='RESUMEN PEDIDO'!$C$30 -> 0 | M73: =(D73*(E73-(E73*K73)))-(D73*(E73-(E73*K73)))*L73 -> 0
B74: 513017 | C74: KINESSENCES RESTORE OVERNIGHT INFUSION | E74: 16 | F74: 17.6 | G74: =VLOOKUP(B74,EAN,3,0) -> 8435057017190 | H74: 150 ml | I74: 6 | J74: =D74/I74 -> 0 | K74: ='RESUMEN PEDIDO'!$C$29 -> 0 | L74: ='RESUMEN PEDIDO'!$C$30 -> 0 | M74: =(D74*(E74-(E74*K74)))-(D74*(E74-(E74*K74)))*L74 -> 0
B75: 513054 | C75: KINESSENCES NOURISH HAND CREAM | E75: 5.8 | F75: 6.4 | G75: 8435057018968 | H75: 50 ml | I75: 12 | J75: =D75/I75 -> 0 | K75: ='RESUMEN PEDIDO'!$C$29 -> 0 | L75: ='RESUMEN PEDIDO'!$C$30 -> 0 | M75: =(D75*(E75-(E75*K75)))-(D75*(E75-(E75*K75)))*L75 -> 0
B76: 513042 | C76: PACK KINESSENCES NOURISH OIL (*) | E76: 43.4 | F76: 47.75 | G76: 8435057018906 | H76: 300 ml + 200 ml + 30 ml | I76: 6 | J76: =D76/I76 -> 0 | K76: ='RESUMEN PEDIDO'!$C$29 -> 0 | L76: ='RESUMEN PEDIDO'!$C$30 -> 0 | M76: =(D76*(E76-(E76*K76)))-(D76*(E76-(E76*K76)))*L76 -> 0
B77: 513043 | C77: PACK KINESSENCES NOURISH OIL CREAM (*) | E77: 44.4 | F77: 48.85 | G77: 8435057018913 | H77: 300 ml + 200 ml + 50 ml | I77: 6 | J77: =D77/I77 -> 0 | K77: ='RESUMEN PEDIDO'!$C$29 -> 0 | L77: ='RESUMEN PEDIDO'!$C$30 -> 0 | M77: =(D77*(E77-(E77*K77)))-(D77*(E77-(E77*K77)))*L77 -> 0
B78: 513040 | C78: PACK KINESSENCES ANTIOX NECTAR (*) | E78: 52.5 | F78: 57.75 | G78: 8435057018883 | H78: 300 ml + 200 ml + 150 ml | I78: 6 | J78: =D78/I78 -> 0 | K78: ='RESUMEN PEDIDO'!$C$29 -> 0 | L78: ='RESUMEN PEDIDO'!$C$30 -> 0 | M78: =(D78*(E78-(E78*K78)))-(D78*(E78-(E78*K78)))*L78 -> 0
B79: 513041 | C79: PACK KINESSENCES ANTIOX SMOOTHIE (*) | E79: 44.4 | F79: 48.85 | G79: 8435057018890 | H79: 300 ml + 200 ml + 50 ml | I79: 6 | J79: =D79/I79 -> 0 | K79: ='RESUMEN PEDIDO'!$C$29 -> 0 | L79: ='RESUMEN PEDIDO'!$C$30 -> 0 | M79: =(D79*(E79-(E79*K79)))-(D79*(E79-(E79*K79)))*L79 -> 0
B80: 513044 | C80: PACK KINESSENCES RESTORE OVERNIGHT INFUSION (*) | E80: 50.5 | F80: 55.55 | G80: 8435057018920 | H80: 300 ml + 200 ml + 150 ml | I80: 6 | J80: =D80/I80 -> 0 | K80: ='RESUMEN PEDIDO'!$C$29 -> 0 | L80: ='RESUMEN PEDIDO'!$C$30 -> 0 | M80: =(D80*(E80-(E80*K80)))-(D80*(E80-(E80*K80)))*L80 -> 0
B81: KINSTYLE / STYLING | D81: =SUM(D82:D89) -> 0 | J81: =SUM(J82:J89) -> 0
B82: 520039 | C82: KINSTYLE CRYSTAL JELLY | E82: 14.8 | F82: 16.3 | G82: =VLOOKUP(B82,EAN,3,0) -> 8435057009256 | H82: 250 ml | I82: 6 | J82: =D82/I82 -> 0 | K82: ='RESUMEN PEDIDO'!$C$29 -> 0 | L82: ='RESUMEN PEDIDO'!$C$30 -> 0 | M82: =(D82*(E82-(E82*K82)))-(D82*(E82-(E82*K82)))*L82 -> 0
B83: 520040 | C83: KINSTYLE MAT GUM | E83: 15 | F83: 16.5 | G83: =VLOOKUP(B83,EAN,3,0) -> 8435057009263 | H83: 100 ml | I83: 6 | J83: =D83/I83 -> 0 | K83: ='RESUMEN PEDIDO'!$C$29 -> 0 | L83: ='RESUMEN PEDIDO'!$C$30 -> 0 | M83: =(D83*(E83-(E83*K83)))-(D83*(E83-(E83*K83)))*L83 -> 0
B84: 520041 | C84: KINSTYLE CURLY CREAM | E84: 14.5 | F84: 15.95 | G84: =VLOOKUP(B84,EAN,3,0) -> 8435057009270 | H84: 150 ml | I84: 6 | J84: =D84/I84 -> 0 | K84: ='RESUMEN PEDIDO'!$C$29 -> 0 | L84: ='RESUMEN PEDIDO'!$C$30 -> 0 | M84: =(D84*(E84-(E84*K84)))-(D84*(E84-(E84*K84)))*L84 -> 0
B85: 520042 | C85: KINSTYLE THERMIC SPRAY | E85: 14.4 | F85: 15.85 | G85: =VLOOKUP(B85,EAN,3,0) -> 8435057009287 | H85: 200 ml | I85: 6 | J85: =D85/I85 -> 0 | K85: ='RESUMEN PEDIDO'!$C$29 -> 0 | L85: ='RESUMEN PEDIDO'!$C$30 -> 0 | M85: =(D85*(E85-(E85*K85)))-(D85*(E85-(E85*K85)))*L85 -> 0
B86: 520056 | C86: KINSTYLE X-TREM ECO SPRAY | E86: 16 | F86: 17.6 | G86: =VLOOKUP(B86,EAN,3,0) -> 8435057009751 | H86: 200 ml | I86: 6 | J86: =D86/I86 -> 0 | K86: ='RESUMEN PEDIDO'!$C$29 -> 0 | L86: ='RESUMEN PEDIDO'!$C$30 -> 0 | M86: =(D86*(E86-(E86*K86)))-(D86*(E86-(E86*K86)))*L86 -> 0
B87: 520060 | C87: KINSTYLE FIBER PASTE | E87: 12 | F87: 13.2 | G87: =VLOOKUP(B87,EAN,3,0) -> 8435057010214 | H87: 100 ml | I87: 6 | J87: =D87/I87 -> 0 | K87: ='RESUMEN PEDIDO'!$C$29 -> 0 | L87: ='RESUMEN PEDIDO'!$C$30 -> 0 | M87: =(D87*(E87-(E87*K87)))-(D87*(E87-(E87*K87)))*L87 -> 0
B88: 520064 | C88: KINSTYLE POTION CREAM | E88: 15 | F88: 16.5 | G88: =VLOOKUP(B88,EAN,3,0) -> 8435057010375 | H88: 150 ml | I88: 6 | J88: =D88/I88 -> 0 | K88: ='RESUMEN PEDIDO'!$C$29 -> 0 | L88: ='RESUMEN PEDIDO'!$C$30 -> 0 | M88: =(D88*(E88-(E88*K88)))-(D88*(E88-(E88*K88)))*L88 -> 0
B89: 520074 | C89: KINSTYLE MAKING WAVES | E89: 16 | F89: 17.6 | G89: =VLOOKUP(B89,EAN,3,0) -> 8435057012034 | H89: 150 ml | I89: 6 | J89: =D89/I89 -> 0 | K89: ='RESUMEN PEDIDO'!$C$29 -> 0 | L89: ='RESUMEN PEDIDO'!$C$30 -> 0 | M89: =(D89*(E89-(E89*K89)))-(D89*(E89-(E89*K89)))*L89 -> 0
B90: HAUTE BY KINSTYLE / STYLING | D90: =SUM(D91:D98) -> 0 | J90: =SUM(J91:J98) -> 0
B91: 520123 | C91: HAUTE SEA SALT MIST | E91: 13 | F91: 14.3 | G91: 8435057020282 | H91: 200 ml | I91: 6 | J91: =D91/I91 -> 0 | K91: ='RESUMEN PEDIDO'!$C$29 -> 0 | L91: ='RESUMEN PEDIDO'!$C$30 -> 0 | M91: =(D91*(E91-(E91*K91)))-(D91*(E91-(E91*K91)))*L91 -> 0
B92: 520124 | C92: HAUTE ESSENTIAL HAIRSPRAY | E92: 20 | F92: 22 | G92: 8435057020305 | H92: 300 ml | I92: 6 | J92: =D92/I92 -> 0 | K92: ='RESUMEN PEDIDO'!$C$29 -> 0 | L92: ='RESUMEN PEDIDO'!$C$30 -> 0 | M92: =(D92*(E92-(E92*K92)))-(D92*(E92-(E92*K92)))*L92 -> 0
B93: 520125 | C93: HAUTE EXTREME HAIRSPRAY | E93: 20 | F93: 22 | G93: 8435057020312 | H93: 300 ml | I93: 6 | J93: =D93/I93 -> 0 | K93: ='RESUMEN PEDIDO'!$C$29 -> 0 | L93: ='RESUMEN PEDIDO'!$C$30 -> 0 | M93: =(D93*(E93-(E93*K93)))-(D93*(E93-(E93*K93)))*L93 -> 0
B94: 520126 | C94: HAUTE ESSENTIAL MOUSSE | E94: 20.5 | F94: 22.55 | G94: 8435057020329 | H94: 300 ml | I94: 6 | J94: =D94/I94 -> 0 | K94: ='RESUMEN PEDIDO'!$C$29 -> 0 | L94: ='RESUMEN PEDIDO'!$C$30 -> 0 | M94: =(D94*(E94-(E94*K94)))-(D94*(E94-(E94*K94)))*L94 -> 0
B95: 520127 | C95: HAUTE EXTREME MOUSSE | E95: 20.5 | F95: 22.55 | G95: 8435057020336 | H95: 300 ml | I95: 6 | J95: =D95/I95 -> 0 | K95: ='RESUMEN PEDIDO'!$C$29 -> 0 | L95: ='RESUMEN PEDIDO'!$C$30 -> 0 | M95: =(D95*(E95-(E95*K95)))-(D95*(E95-(E95*K95)))*L95 -> 0
B96: 520128 | C96: HAUTE RADICAL VOLUME | E96: 21.5 | F96: 23.65 | G96: 8435057020343 | H96: 300 ml | I96: 6 | J96: =D96/I96 -> 0 | K96: ='RESUMEN PEDIDO'!$C$29 -> 0 | L96: ='RESUMEN PEDIDO'!$C$30 -> 0 | M96: =(D96*(E96-(E96*K96)))-(D96*(E96-(E96*K96)))*L96 -> 0
B97: 520087 | C97: HAUTE THICKENING CREAM | E97: 14.8 | F97: 16.3 | G97: =VLOOKUP(B97,EAN,3,0) -> 8435057014762 | H97: 150 ml | I97: 6 | J97: =D97/I97 -> 0 | K97: ='RESUMEN PEDIDO'!$C$29 -> 0 | L97: ='RESUMEN PEDIDO'!$C$30 -> 0 | M97: =(D97*(E97-(E97*K97)))-(D97*(E97-(E97*K97)))*L97 -> 0
B98: 520088 | C98: HAUTE DRY SHAMPOO & VOLUME POWDER | E98: 21.5 | F98: 23.65 | G98: 8435057014779 | H98: 300 ml | I98: 6 | J98: =D98/I98 -> 0 | K98: ='RESUMEN PEDIDO'!$C$29 -> 0 | L98: ='RESUMEN PEDIDO'!$C$30 -> 0 | M98: =(D98*(E98-(E98*K98)))-(D98*(E98-(E98*K98)))*L98 -> 0
B99: KINWORKS / STYLING | D99: =SUM(D100:D100) -> 0 | J99: =SUM(J100:J100) -> 0
B100: 530037 | C100: KINWORKS SHAPING WET | E100: 15 | F100: 16.5 | G100: =VLOOKUP(B100,EAN,3,0) -> 8435057016971 | H100: 400 ml | I100: 6 | J100: =D100/I100 -> 0 | K100: ='RESUMEN PEDIDO'!$C$29 -> 0 | L100: ='RESUMEN PEDIDO'!$C$30 -> 0 | M100: =(D100*(E100-(E100*K100)))-(D100*(E100-(E100*K100)))*L100 -> 0
B101: (*) Hasta fin de existencias.

Sheet MATERIAL MARKETING
B1: KIN COSMETICS, S.A.U.
B2: HOJA DE PEDIDO DISTRIBUIDOR | F2: CRÉDITO | H2: ='[1]RESUMEN PEDIDO'!H41 -> 0
F3: DIFERENCIA | H3: ='RESUMEN PEDIDO'!H45 -> 0
B6: MATERIAL MARKETING
B7: SUBTOTAL MATERIAL MARKETING | D7: =SUBTOTAL(9,D9:D147) -> 0 | H7: =SUBTOTAL(9,H9:H147) -> 0
B8: Ref. | C8: Descripción | D8: Unidades | E8: Precio Tarifa | F8: Formato | G8: Dto. | H8: Subtotal
B9: MATERIAL PROMOCIONAL / DESECHABLES
B10: 310255 | C10: CAPAS DESECHABLES KIN WE LOVE HAIR | E10: 17.07619 | F10: Caja 50 uds. | G10: ='[1]RESUMEN PEDIDO'!$C$31 -> 0.7 | H10: =(D10*(E10-(E10*G10))) -> 0
B11: 310280 | C11: GORROS DESECHABLES MECHAS KIN WE LOVE HAIR (*) | E11: 6.9840048 | F11: Bolsa 50 uds. | G11: ='[1]RESUMEN PEDIDO'!$C$31 -> 0.7 | H11: =(D11*(E11-(E11*G11))) -> 0
B12: MATERIAL PROMOCIONAL / ELÉCTRICOS
B13: 310388 | C13: PLANCHA PROFESIONAL KIN LATTE EDITION | E13: 96.904762 | F13: Unidad | G13: ='[1]RESUMEN PEDIDO'!$C$31 -> 0.7 | H13: =(D13*(E13-(E13*G13))) -> 0
B14: MATERIAL PROMOCIONAL / UTENSILIOS
B15: 310148 | C15: BOL COLORACIÓN KIN NEGRO | E15: 1.7652381 | F15: Unidad | G15: ='[1]RESUMEN PEDIDO'!$C$31 -> 0.7 | H15: =(D15*(E15-(E15*G15))) -> 0
B16: 310326 | C16: PALETINA COLOR KIN NEGRA - TALLA M | E16: 1.8333333 | F16: Unidad | G16: ='[1]RESUMEN PEDIDO'!$C$31 -> 0.7 | H16: =(D16*(E16-(E16*G16))) -> 0
B17: 310327 | C17: PALETINA COLOR KIN NEGRA - TALLA L | E17: 1.8333333 | F17: Unidad | G17: ='[1]RESUMEN PEDIDO'!$C$31 -> 0.7 | H17: =(D17*(E17-(E17*G17))) -> 0
B18: 310362 | C18: BOTELLA APLICADORA COLOR KIN | E18: 4.3140952 | F18: Unidad | G18: ='[1]RESUMEN PEDIDO'!$C$31 -> 0.7 | H18: =(D18*(E18-(E18*G18))) -> 0
B19: 310352 | C19: BOL TRATAMIENTOS KIN BLANCO | E19: 6.2857143 | F19: Unidad | G19: ='[1]RESUMEN PEDIDO'!$C$31 -> 0.7 | H19: =(D19*(E19-(E19*G19))) -> 0
B20: 310353 | C20: PALETINA TRATAMIENTOS KIN BLANCA | E20: 1.3095238 | F20: Unidad | G20: ='[1]RESUMEN PEDIDO'!$C$31 -> 0.7 | H20: =(D20*(E20-(E20*G20))) -> 0
B21: 310400 | C21: ESPATULA TRATAMIENTOS KIN | E21: 0.62857143 | F21: Unidad | G21: ='[1]RESUMEN PEDIDO'!$C$31 -> 0.7 | H21: =(D21*(E21-(E21*G21))) -> 0
B22: 310393 | C22: CEPILLO MASAJEADOR DE CUERO CABELLUDO KIN | E22: 3.352381 | F22: Unidad | G22: ='[1]RESUMEN PEDIDO'!$C$31 -> 0.7 | H22: =(D22*(E22-(E22*G22))) -> 0
B23: 310392 | C23: PEINE MECHAS KIN BABYLIGHTS | E23: 2.7238095 | F23: Unidad | G23: ='[1]RESUMEN PEDIDO'!$C$31 -> 0.7 | H23: =(D23*(E23-(E23*G23))) -> 0
B24: 310355 | C24: CAPA DE CORTE KIN NEGRA | E24: 25.195238 | F24: Unidad | G24: ='[1]RESUMEN PEDIDO'!$C$31 -> 0.7 | H24: =(D24*(E24-(E24*G24))) -> 0
B25: 310244 | C25: ESPEJO KIN WE LOVE HAIR (*) | E25: 13.357143 | F25: Unidad | G25: ='[1]RESUMEN PEDIDO'!$C$31 -> 0.7 | H25: =(D25*(E25-(E25*G25))) -> 0
B26: 310328 | C26: VÁLVULA SHAMPOO 1.000 ML KINACTIF | E26: 1.1561 | F26: Unidad | G26: ='[1]RESUMEN PEDIDO'!$C$31 -> 0.7 | H26: =(D26*(E26-(E26*G26))) -> 0
... B31: 310332 | C31: TAPÓN DOSIFICADOR NEGRO OXIDANTES / DEVELOPERS 1.000 ML | E31: 0.25698095 | F31: Unidad | G31: ='[1]RESUMEN PEDIDO'!$C$31 -> 0.7 | H31: =(D31*(E31-(E31*G31))) -> 0
B32: MATERIAL PROMOCIONAL / COMUNICACIÓN
B33: 300865 | C33: CATÁLOGO PRODUCT PORTFOLIO (Edición Marzo 2025) | E33: 4.5204762 | F33: A4 | G33: ='[1]RESUMEN PEDIDO'!$C$31 -> 0.7 | H33: =(D33*(E33-(E33*G33))) -> 0
B34: 300909 | C34: TARIFA PVP 2026 | E34: 1.87 | F34: 24 x 14,5 cm | G34: ='[1]RESUMEN PEDIDO'!$C$31 -> 0.7 | H34: =(D34*(E34-(E34*G34))) -> 0
B35: 300904 | C35: DOOR STICKER KIN COSMÉTICA DE PROXIMIDAD | E35: 5.222381 | F35: Ø 24 cm | G35: ='[1]RESUMEN PEDIDO'!$C$31 -> 0.7 | H35: =(D35*(E35-(E35*G35))) -> 0
B36: 300710 | C36: CARTA COLOR KINCREM COLOR - 120 TONOS | E36: 71.395238 | F36: 40 x 24 cm | G36: ='[1]RESUMEN PEDIDO'!$C$31 -> 0.7 | H36: =(D36*(E36-(E36*G36))) -> 0
B37: 300714 | C37: QUICK COLOR GUIDE KINCREM COLOR (*) | E37: 2.5525238 | F37: A4 | G37: ='[1]RESUMEN PEDIDO'!$C$31 -> 0.7 | H37: =(D37*(E37-(E37*G37))) -> 0
B38: 300716 | C38: FOLDER TÉCNICO KINCREM COLOR | E38: 4.3144095 | F38: A4 | G38: ='[1]RESUMEN PEDIDO'!$C$31 -> 0.7 | H38: =(D38*(E38-(E38*G38))) -> 0
B39: 300732 | C39: BANNER TEXTIL KINCREM COLOR MODELO 2 (*) | E39: 40.912824 | F39: 50 x 110 cm | G39: ='[1]RESUMEN PEDIDO'!$C$31 -> 0.7 | H39: =(D39*(E39-(E39*G39))) -> 0
B40: 300883 | C40: FOLDER TÉCNICO MOCHA MOUSSE COLLECTION by KINCREM COLOR (*) | E40: 3.6142857 | F40: A4 | G40: ='[1]RESUMEN PEDIDO'!$C$31 -> 0.7 | H40: =(D40*(E40-(E40*G40))) -> 0
B41: 300829 | C41: CARTA COLOR KINESSENCES COLOR VEGAN - 69 TONOS | E41: 68.042857 | F41: 24 x 40 cm | G41: ='[1]RESUMEN PEDIDO'!$C$31 -> 0.7 | H41: =(D41*(E41-(E41*G41))) -> 0
B42: 300761 | C42: QUICK COLOR GUIDE KINESSENCES COLOR VEGAN (*) | E42: 2.9333333 | F42: A4 | G42: ='[1]RESUMEN PEDIDO'!$C$31 -> 0.7 | H42: =(D42*(E42-(E42*G42))) -> 0
B43: 300762 | C43: FOLDER TÉCNICO KINESSENCES COLOR VEGAN | E43: 3.5457714 | F43: 1 | G43: ='[1]RESUMEN PEDIDO'!$C$31 -> 0.7 | H43: =(D43*(E43-(E43*G43))) -> 0
B44: 300759 | C44: DOOR STICKER KINESSENCES COLOR VEGAN (*) | E44: 20.577333 | F44: Ø 24 cm | G44: ='[1]RESUMEN PEDIDO'!$C$31 -> 0.7 | H44: =(D44*(E44-(E44*G44))) -> 0
B45: 300783 | C45: VINILO CHICA KINESSENCES COLOR (*) | E45: 28.432381 | F45: 90 x 65 cm | G45: ='[1]RESUMEN PEDIDO'!$C$31 -> 0.7 | H45: =(D45*(E45-(E45*G45))) -> 0
B46: 300832 | C46: CARTA COLOR KINGLOSS COLOR | E46: 54.47619 | F46: 35,6 x 16,2 cm | G46: ='[1]RESUMEN PEDIDO'!$C$31 -> 0.7 | H46: =(D46*(E46-(E46*G46))) -> 0
B47: 300806 | C47: FOLDER TÉCNICO KINGLOSS COLOR | E47: 3.8658714 | F47: A4 | G47: ='[1]RESUMEN PEDIDO'!$C$31 -> 0.7 | H47: =(D47*(E47-(E47*G47))) -> 0
B48: 300812 | C48: MENÚ SERVICIOS KINGLOSS COLOR | E48: 2.2943381 | F48: 14,5 x 29 cm | G48: ='[1]RESUMEN PEDIDO'!$C$31 -> 0.7 | H48: =(D48*(E48-(E48*G48))) -> 0
B49: 300808 | C49: DISPLAY KINGLOSS COLOR (*) | E49: 19.833262 | F49: 94,5 x 64 cm | G49: ='[1]RESUMEN PEDIDO'!$C$31 -> 0.7 | H49: =(D49*(E49-(E49*G49))) -> 0
B50: 300807 | C50: DOOR STICKER KINGLOSS COLOR (*) | E50: 12.62381 | F50: Ø 24 cm | G50: ='[1]RESUMEN PEDIDO'!$C$31 -> 0.7 | H50: =(D50*(E50-(E50*G50))) -> 0
B51: 300795 | C51: FOLDER TÉCNICO KINMASTER | E51: 4.3947095 | F51: A4 | G51: ='[1]RESUMEN PEDIDO'!$C$31 -> 0.7 | H51: =(D51*(E51-(E51*G51))) -> 0
B52: 300731 | C52: FOLDER TÉCNICO KINPERM | E52: 2.0252571 | F52: A4 | G52: ='[1]RESUMEN PEDIDO'!$C$31 -> 0.7 | H52: =(D52*(E52-(E52*G52))) -> 0
B53: 300827 | C53: FOLDER TÉCNICO KINSMOOTH (*) | E53: 3.8761905 | F53: A4 | G53: ='[1]RESUMEN PEDIDO'!$C$31 -> 0.7 | H53: =(D53*(E53-(E53*G53))) -> 0
B54: 300837 | C54: DISPLAY SOBREMESA KINSMOOTH MECHAS (*) | E54: 26.452381 | F54: 17,8 x 30,5 x 6,3 cm | G54: ='[1]RESUMEN PEDIDO'!$C$31 -> 0.7 | H54: =(D54*(E54-(E54*G54))) -> 0
B55: 300852 | C55: FOLDER TÉCNICO KINBLOND | E55: 3.2895238 | F55: A4 | G55: ='[1]RESUMEN PEDIDO'!$C$31 -> 0.7 | H55: =(D55*(E55-(E55*G55))) -> 0
... B79: 300729 | C79: FOLLETO KINMEN RETAIL (*) | E79: 0.64690476 | F79: 9 x 16 cm | G79: ='[1]RESUMEN PEDIDO'!$C$31 -> 0.7 | H79: =(D79*(E79-(E79*G79))) -> 0
B80: MATERIAL PROMOCIONAL / EXPOSICIÓN
B81: 300856 | C81: GLORIFICADOR METACRILATO KIN | E81: 33 | F81: 21 x 15 x 30 cm | G81: ='[1]RESUMEN PEDIDO'!$C$31 -> 0.7 | H81: =(D81*(E81-(E81*G81))) -> 0
B82: 300859 | C82: PÓSTER BIENVENIDX A NUESTRO UNIVERSO BEAUTY (para glorificador metacrilato) (*) | E82: 0.88 | F82: A4 | G82: ='[1]RESUMEN PEDIDO'!$C$31 -> 0.7 | H82: =(D82*(E82-(E82*G82))) -> 0
B83: 300866 | C83: PÓSTER KINBLOND (para glorificador metacrilato) (*) | E83: 0.88 | F83: A4 | G83: ='[1]RESUMEN PEDIDO'!$C$31 -> 0.7 | H83: =(D83*(E83-(E83*G83))) -> 0
B84: 300858 | C84: PÓSTER KINACTIF Nº8 SCALP (para glorificador metacrilato) (*) | E84: 0.88 | F84: A4 | G84: ='[1]RESUMEN PEDIDO'!$C$31 -> 0.7 | H84: =(D84*(E84-(E84*G84))) -> 0
B85: 300781 | C85: EXPOSITOR PERMANENTE KIN - BLANCO Y ROBLE | E85: 967.37 | F85: 52,5 x 40 x 180 cm | G85: ='[1]RESUMEN PEDIDO'!$C$31 -> 0.7 | H85: =(D85*(E85-(E85*G85))) -> 0
B86: 300780 | C86: EXPOSITOR SOBREMESA KINACTIF (*) | E86: 28.495238 | F86: 30 x 29 x 21 cm | G86: ='[1]RESUMEN PEDIDO'!$C$31 -> 0.7 | H86: =(D86*(E86-(E86*G86))) -> 0
B87: 300804 | C87: EXPOSITOR SOBREMESA KINESSECES (*) | E87: 26.871429 | F87: 26,5 x 30 x 21 cm | G87: ='[1]RESUMEN PEDIDO'!$C$31 -> 0.7 | H87: =(D87*(E87-(E87*G87))) -> 0
B88: 300763 | C88: EXPOSITOR KIN PIE MODELO 1 - IMAGEN KINCREM COLOR (*) | E88: 201.4781 | F88: 39 x 39 x 130 cm | G88: ='[1]RESUMEN PEDIDO'!$C$31 -> 0.7 | H88: =(D88*(E88-(E88*G88))) -> 0
B89: 300764 | C89: EXPOSITOR KIN PIE MODELO 2 - IMAGEN KINESSENCES (*) | E89: 201.4781 | F89: 39 x 39 x 130 cm | G89: ='[1]RESUMEN PEDIDO'!$C$31 -> 0.7 | H89: =(D89*(E89-(E89*G89))) -> 0
B90: 300815 | C90: GLORIFICADOR KINGLOSS COLOR (*) | E90: 27.604762 | F90: 20 x 22 x 11cm | G90: ='[1]RESUMEN PEDIDO'!$C$31 -> 0.7 | H90: =(D90*(E90-(E90*G90))) -> 0
B91: 300727 | C91: EXPOSITOR SOBREMESA KINMEN (*) | E91: 23.303657 | F91: 26,5 x 30 x 21 cm | G91: ='[1]RESUMEN PEDIDO'!$C$31 -> 0.7 | H91: =(D91*(E91-(E91*G91))) -> 0
B92: MATERIAL PROMOCIONAL / REGALOS
B93: 300887 | C93: MINI CEPILLO KIN ROSA (*) | E93: 2.6930619 | F93: 15 x 6 x 3 cm | G93: ='[1]RESUMEN PEDIDO'!$C$31 -> 0.7 | H93: =(D93*(E93-(E93*G93))) -> 0
B94: 300888 | C94: MINI CEPILLO KIN LILA (*) | E94: 2.6930619 | F94: 15 x 6 x 3 cm | G94: ='[1]RESUMEN PEDIDO'!$C$31 -> 0.7 | H94: =(D94*(E94-(E94*G94))) -> 0
B95: 310422 | C95: PAREO BEIGE KIN MADE IN COSTA BRAVA (*) | E95: 20.732381 | F95: 100 x 180 cm | G95: ='[1]RESUMEN PEDIDO'!$C$31 -> 0.7 | H95: =(D95*(E95-(E95*G95))) -> 0
B96: 310345 | C96: SCRUNCHIE KIN WE LOVE HAIR MARRÓN (*) | E96: 3.682381 | F96: Unidad | G96: ='[1]RESUMEN PEDIDO'!$C$31 -> 0.7 | H96: =(D96*(E96-(E96*G96))) -> 0
B97: 310346 | C97: SCRUNCHIE KIN WE LOVE HAIR ROSA (*) | E97: 3.682381 | F97: Unidad | G97: ='[1]RESUMEN PEDIDO'!$C$31 -> 0.7 | H97: =(D97*(E97-(E97*G97))) -> 0
B98: 310347 | C98: SCRUNCHIE KIN WE LOVE HAIR AZUL (*) | E98: 3.682381 | F98: Unidad | G98: ='[1]RESUMEN PEDIDO'!$C$31 -> 0.7 | H98: =(D98*(E98-(E98*G98))) -> 0
B99: MATERIAL PROMOCIONAL / REVENTA
B100: 511129 | C100: MINI TALLA KINACTIF MOISTURIZING CONDITIONING SPRAY | E100: 3.0584058 | F100: 50 ml | G100: ='[1]RESUMEN PEDIDO'!$C$31 -> 0.7 | H100: =(D100*(E100-(E100*G100))) -> 0
B101: 511033 | C101: MINI TALLA KINACTIF DAILY MOISTURIZING SHAMPOO | E101: 2.6817015 | F101: 50 ml | G101: ='[1]RESUMEN PEDIDO'!$C$31 -> 0.7 | H101: =(D101*(E101-(E101*G101))) -> 0
B102: 511057 | C102: MINI TALLA KINACTIF RICH NOURISHING SHAMPOO | E102: 2.6817015 | F102: 50 ml | G102: ='[1]RESUMEN PEDIDO'!$C$31 -> 0.7 | H102: =(D102*(E102-(E102*G102))) -> 0
B103: 511042 | C103: MINI TALLA KINACTIF RICH RECONSTRUCTING SHAMPOO | E103: 2.6817015 | F103: 50 ml | G103: ='[1]RESUMEN PEDIDO'!$C$31 -> 0.7 | H103: =(D103*(E103-(E103*G103))) -> 0
B104: 511131 | C104: MINI TALLA KINACTIF RECONSTRUCTING 2-IN-1 MASK (*) | E104: 3.2551603 | F104: 50 ml | G104: ='[1]RESUMEN PEDIDO'!$C$31 -> 0.7 | H104: =(D104*(E104-(E104*G104))) -> 0
B105: 511043 | C105: MINI TALLA KINACTIF MILD EXPANDING SHAMPOO | E105: 2.6817015 | F105: 50 ml | G105: ='[1]RESUMEN PEDIDO'!$C$31 -> 0.7 | H105: =(D105*(E105-(E105*G105))) -> 0
B106: 511069 | C106: MINI TALLA KINACTIF COLOR PROTECTING SHAMPOO | E106: 2.6817015 | F106: 50 ml | G106: ='[1]RESUMEN PEDIDO'!$C$31 -> 0.7 | H106: =(D106*(E106-(E106*G106))) -> 0
B107: 511056 | C107: MINI TALLA KINACTIF ANTI-BRASS BLONDE SHAMPOO | E107: 2.6817015 | F107: 50 ml | G107: ='[1]RESUMEN PEDIDO'!$C$31 -> 0.7 | H107: =(D107*(E107-(E107*G107))) -> 0
B108: 511093 | C108: MINI TALLA KINACTIF CURL ENHANCING SHAMPOO | E108: 2.6817015 | F108: 50 ml | G108: ='[1]RESUMEN PEDIDO'!$C$31 -> 0.7 | H108: =(D108*(E108-(E108*G108))) -> 0
B109: 511094 | C109: MINI TALLA KINACTIF INTENSE SOFTENING SHAMPOO | E109: 2.6817015 | F109: 50 ml | G109: ='[1]RESUMEN PEDIDO'!$C$31 -> 0.7 | H109: =(D109*(E109-(E109*G109))) -> 0
B110: 511132 | C110: MINI TALLA KINACTIF AFTERSUN SHAMPOO & SHOWER GEL (*) | E110: 2.6817015 | F110: 50 ml | G110: ='[1]RESUMEN PEDIDO'!$C$31 -> 0.7 | H110: =(D110*(E110-(E110*G110))) -> 0
B111: 511133 | C111: MINI TALLA KINACTIF AFTERSUN 2-IN-1 MASK (*) | E111: 3.2551603 | F111: 50 ml | G111: ='[1]RESUMEN PEDIDO'!$C$31 -> 0.7 | H111: =(D111*(E111-(E111*G111))) -> 0
... B147: 300799 | C147: KINBOX KIN WE LOVE HAIR (*) | E147: 4.6290619 | F147: 30 x 11 x 32,5 cm | G147: ='[1]RESUMEN PEDIDO'!$C$31 -> 0.7 | H147: =(D147*(E147-(E147*G147))) -> 0
B148: (*) Hasta fin de existencias.

Sheet PRODUCTO OUTLET
B1: KIN COSMETICS, S.A.U.
B2: HOJA DE PEDIDO DISTRIBUIDOR
B6: PRODUCTO OUTLET
B7: SUBTOTAL PRODUCTO OUTLET | D7: =D9+D13+D17 -> 0 | I7: =I9+I13+I17 -> 0 | J7: =SUBTOTAL(9,J9:J23) -> 0
B8: Ref. | C8: Descripción | D8: Unidades | E8: Precio Neto | F8: Código EAN | G8: Formato | H8: Packing | I8: Cajas | J8: Subtotal
B9: EARTH NUDES COLLECTION BY KINCREM PRESTIGE / COLORACIÓN | D9: =SUM(D10:D12) -> 0 | H9: 36 | I9: =SUM(I10:I12) -> 0
B10: 501140 | C10: EARTH NUDES COLLECTION 7.512 SAHARA NUDE | E10: 3.6 | F10: =VLOOKUP(B10,EAN,3,0) -> 8435057014021 | G10: 3 x 60 ml | H10: 36 | I10: =D10/H10 -> 0 | J10: =D10*E10 -> 0
B11: 501141 | C11: EARTH NUDES COLLECTION 8.348 NAMBUNG OCHER | E11: 3.6 | F11: =VLOOKUP(B11,EAN,3,0) -> 8435057014038 | G11: 3 x 60 ml | H11: 36 | I11: =D11/H11 -> 0 | J11: =D11*E11 -> 0
B12: 501142 | C12: EARTH NUDES COLLECTION 8.762 JORDAN ROSE | E12: 3.6 | F12: =VLOOKUP(B12,EAN,3,0) -> 8435057014045 | G12: 3 x 60 ml | H12: 36 | I12: =D12/H12 -> 0 | J12: =D12*E12 -> 0
B13: RUST COLLECTION BY KINESSENCES COLOR / COLORACIÓN | D13: =SUM(D14:D16) -> 0 | H13: 36 | I13: =D13/H13 -> 0
B14: 512183 | C14: RUST COLLECTION 5.519 ASHY BROWN | E14: 3.5 | F14: =VLOOKUP(B14,EAN,3,0) -> 8435057014694 | G14: 3 x 60 ml | H14: 36 | I14: =D14/H14 -> 0 | J14: =D14*E14 -> 0
B15: 512184 | C15: RUST COLLECTION 6.762 PURPLE DUST | E15: 3.5 | F15: =VLOOKUP(B15,EAN,3,0) -> 8435057014700 | G15: 3 x 60 ml | H15: 36 | I15: =D15/H15 -> 0 | J15: =D15*E15 -> 0
B16: 512185 | C16: RUST COLLECTION 7.456 OXIDE AMBER | E16: 3.5 | F16: =VLOOKUP(B16,EAN,3,0) -> 8435057014717 | G16: 3 x 60 ml | H16: 36 | I16: =D16/H16 -> 0 | J16: =D16*E16 -> 0
B17: KINACTIF / TRATAMIENTOS | D17: =SUM(D18:D23) -> 0 | I17: =SUM(I18:I19) -> 0
B18: 510142 | C18: KINACTIF ENERGY RECONSTRUCTOR | E18: 4 | F18: 8435057006767 | G18: 150 ml | H18: 6 | I18: =D18/H18 -> 0 | J18: =D18*E18 -> 0
B19: 510161 | C19: KINACTIF NUTRI SERUM | E19: 4.5 | F19: =VLOOKUP(B19,EAN,3,0) -> 8435057006958 | G19: 50 ml | H19: 6 | I19: =D19/H19 -> 0 | J19: =D19*E19 -> 0
B20: 510170 | C20: KINACTIF FORCE COMPLEXE TRICO-ACTIVE (*) | E20: 14.7 | F20: 8435057007047 | G20: 12 x 6 ml | H20: 6 | I20: =D20/H20 -> 0 | J20: =D20*E20 -> 0
B21: 510175 | C21: KINACTIF PURITY TONIC | E21: 4.5 | F21: 8435057007092 | G21: 150 ml | H21: 6 | I21: =D21/H21 -> 0 | J21: =D21*E21 -> 0
B22: 510179 | C22: KINACTIF BALANCE TONIC | E22: 4.5 | F22: 8435057007146 | G22: 150 ml | H22: 6 | I22: =D22/H22 -> 0 | J22: =D22*E22 -> 0
B23: 510332 | C23: KINACTIF CALM SHAMPOO | E23: 2.8 | F23: 8435057015158 | G23: 300 ml | H23: 6 | I23: =D23/H23 -> 0 | J23: =D23*E23 -> 0
B24: Precios netos (no aplican descuentos). Todos los artículos son hasta fin de existencias

Sheet MATERIAL MKT OUTLET
B1: KIN COSMETICS, S.A.U.
B2: HOJA DE PEDIDO DISTRIBUIDOR | F2: CRÉDITO | G2: ='RESUMEN PEDIDO'!H54 -> 0
F3: DIFERENCIA | G3: ='RESUMEN PEDIDO'!H58 -> 0
B6: MATERIAL MARKETING OUTLET
B7: SUBTOTAL MATERIAL MARKETING OUTLET | D7: =SUBTOTAL(9,D10:D29) -> 0 | G7: =SUBTOTAL(9,G10:G29) -> 0
B8: Ref. | C8: Descripción | D8: Unidades | E8: Precio Outlet | F8: Formato | G8: Subtotal
B9: MATERIAL PROMOCIONAL / UTENSILIOS
B10: 390015 | C10: PACK 4 PINZAS SILICONA ROSA FRAMAR | E10: 3.32 | F10: Unidad | G10: =E10*D10 -> 0
B11: MATERIAL PROMOCIONAL / COMUNICACIÓN
B12: 300640 | C12: CARTA EARTH NUDES COLLECTION BY KINCREM PRESTIGE | E12: 6.02 | F12: 18 x 28 cm | G12: =E12*D12 -> 0
B13: 300641 | C13: KIT PRESENTACIÓN EARTH NUDES COLLECTION BY KINCREM PRESTIGE (prod. incl.) | E13: 7.03 | F13: 26,5 x 22,5 x 3 cm | G13: =E13*D13 -> 0
B14: 300643 | C14: DISPLAY DOBLE ALA EARTH NUDES COLLECTION BY KINCREM PRESTIGE | E14: 2.49 | F14: 66 x 96 cm | G14: =E14*D14 -> 0
B15: 300521 | C15: CARTA COLOR KINESSENCES COLOR | E15: 12.46 | F15: 24 x 40 cm | G15: =E15*D15 -> 0
B16: 300524 | C16: KINESSENCES COLOR QUICK COLOR GUIDE | E16: 0.39 | F16: A4 | G16: =E16*D16 -> 0
B17: 300549 | C17: FOLLETO KINESSENCES DETOX RETAIL | E17: 0.04 | F17: 10,5 x 15 cm | G17: =E17*D17 -> 0
B18: 300636 | C18: FOLDER TÉCNICO KINESSENCES RESTORE | E18: 0.62 | F18: A4 | G18: =E18*D18 -> 0
B19: 300639 | C19: FOLLETO MINI KINESSENCES RESTORE | E19: 0.08 | F19: 8 x 10 cm | G19: =E19*D19 -> 0
B20: 300735 | C20: DIPTICO KINESSENCES RESTORE RETAIL | E20: 0.1 | F20: A4 | G20: =E20*D20 -> 0
B21: 300733 | C21: DIPTICO KINACTIF FORCE RETAIL | E21: 0.1 | F21: A4 | G21: =E21*D21 -> 0
B22: 300674 | C22: CARTA RUST COLLECTION BY KINESSENCES COLOR | E22: 3.56 | F22: 18 x 28 cm | G22: =E22*D22 -> 0
B23: 300675 | C23: KIT PRESENTACIÓN RUST COLLECTION BY KINESSENCES COLOR (prod. incl.) | E23: 8.635 | F23: 26,5 x 22,5 x 3 cm | G23: =E23*D23 -> 0
B24: 300690 | C24: FOLDER TÉCNICO RUST COLLECTION | E24: 0.2288 | F24: A4 | G24: =E24*D24 -> 0
B25: 300677 | C25: DISPLAY DOBLE ALA RUST COLLECTION BY KINESSENCES COLOR | E25: 2.32 | F25: 66 x 96 cm | G25: =E25*D25 -> 0
B26: MATERIAL PROMOCIONAL / REVENTA
B27: 510236 | C27: SACHET CALM SHAMPOO | E27: 0.2 | F27: 8 ml | G27: =E27*D27 -> 0
B28: 310279 | C28: BOLSA REVENTA KINESSENCES RESTORE | E28: 0.53 | F28: Unidad | G28: =E28*D28 -> 0
B29: 310340 | C29: COOLER BAG KINACTIF SUNCARE | E29: 2.83 | F29: 34 x 21 x 26 cm | G29: =E29*D29 -> 0
B30: Todos los artículos son hasta fin de existencias.

Sheet EAN
A1: CÓDIGOS EAN
A3: Nº producto | B3: Descripción Producto | C3: Nº referencia cruzada
A4: 11000 | B4: AGUA DESIONIZADA Lts. | C4: LIAGUA
A5: 11001 | B5: CARBOPOL 980 | C5: SPC940
A6: 11002 | B6: EASYCOL ES27 | C6: TESDSS
A7: 11002 | B7: EASYCOL ES27 | C7: 11002
A8: 11002 | B8: EASYCOL ES27 | C8: 11002
A9: 11003 | B9: DABEERSEN NA4 C2 / NA4 TD | C9: CNDANA
A10: 11003 | B10: DABEERSEN NA4 C2 / NA4 TD | C10: CNDANA
A11: 11004 | B11: JAGUAR C-13 SH | C11: POJA13
A12: 11005 | B12: EASYLAN LS / NEOWAX SX/W | C12: 11005
A13: 11005 | B13: EASYLAN LS / NEOWAX SX/W | C13: 11005
A14: 11005 | B14: EASYLAN LS / NEOWAX SX/W | C14: 11005
A15: 11006 | B15: MIRASIL 60000 | C15: MIRASIL 60000
... A350: 11359 | B350: DAPRACARE GMS-35-SE | C350: 11359
A351: 11381 | B351: QUINOA PRO NPNF
A352: 11401 | B352: DAPRACARE GMS 35 SE (ES 11359) | C352: 11401
A353: 11401 | B353: DAPRACARE GMS 35 SE (ES 11359) | C353: 11401
A354: 12000 | B354: RESORCINOL TECH.GRADE FLAKES | C354: RODOL
A355: 12000 | B355: RESORCINOL TECH.GRADE FLAKES | C355: JARCOCOL
A356: 12000 | B356: RESORCINOL TECH.GRADE FLAKES | C356: CORESO
A357: 12000 | B357: RESORCINOL TECH.GRADE FLAKES | C357: CORESO
A358: 12001 | B358: RODOL 4BXN | C358: CO4BXN
A359: 12002 | B359: LOWACRYL BLUE 7 | C359: COBLU7
A360: 12003 | B360: LOWACRYL BLUE 9 | C360: COBLU9
A361: 12004 | B361: RODOL GRAY HED | C361: COGRHE
A362: 12004 | B362: RODOL GRAY HED | C362: COGRHE
A363: 12005 | B363: HC BLUE 2 CP | C363: COHCB2
... A525: 13089 | B525: PERFUME AMBER 2004747 | C525: PFAMBE
A526: 13090 | B526: PERFUME NIPPER FRESH 5470K
A527: 13091 | B527: PERF FRESH BALSAM INC.2004858 | C527: PFFRBA
A528: 13092 | B528: PERFUME NATURAL 2005388 | C528: PFNATU
A529: 13093 | B529: PERFUME IRIS TINT 30130 | C529: PFIRTI
A530: 13094 | B530: PERF. SH.NEW MARACUYA 21394 | C530: PFNEMASH
A531: 13095 | B531: PERF. SH. TEI ORANGE 12072 | C531: PFTEORSH
A532: 13096 | B532: HAVEN | C532: PFHAVE
A533: 13097 | B533: CUHERBAL 1104980 | C533: PFCUHE
A534: 13098 | B534: HERBALFRESH 1119950 | C534: PFHERB
A535: 13099 | B535: COOL M 2005072 | C535: PFCOOL
A536: 13100 | B536: COOL BLUE 17673 | C536: PFCLBL
A537: 13101 | B537: MINGUN 23602 | C537: PFMING
A538: 13101 | B538: MINGUN 23602
A539: 200001 | B539: BOT. 1000 ML. AZUL NACAR KA | C539: BO10A
A540: 200001 | B540: BOT. 1000 ML. AZUL NACAR KA | C540: 200001
A541: 200002 | B541: BOT. 1000 ML. KA AMARILLO | C541: BO10B
A542: 200002 | B542: BOT. 1000 ML. KA AMARILLO | C542: 200002
A543: 200003 | B543: BOT. CUTI FORTE SHAMP 1000 ml. | C543: BO10CFSH
A544: 200003 | B544: BOT. CUTI FORTE SHAMP 1000 ml. | C544: 200003
A545: 200004 | B545: BOT. CUTI-GLOSS SHAMP 1000 ml. | C545: BO10CGSH
A546: 200004 | B546: BOT. CUTI-GLOSS SHAMP 1000 ml. | C546: 200004
A547: 200005 | B547: BOT. CASP SECA SHAMP 1000 ml. | C547: BO10CSSH
A548: 200005 | B548: BOT. CASP SECA SHAMP 1000 ml. | C548: 200005
A549: 200006 | B549: BOT. 1000 ML. KA GRIS PLATA | C549: BO10G
A550: 200006 | B550: BOT. 1000 ML. KA GRIS PLATA | C550: 200006
... A8417: 790075 | B8417: PULP RIOT BLEACH LIGHTENER 500G | C8417: 0857472006258
A8418: 790076 | B8418: PULP RIOT CLAY LIGHTENER 500G.
A8419: 790076 | B8419: PULP RIOT CLAY LIGHTENER 500G. | C8419: 0857472006432
A8420: 790077 | B8420: PULP RIOT BLANK CANVAS 45 GRS. | C8420: GLCOLORREMOVER
A8421: 790077 | B8421: PULP RIOT BLANK CANVAS 45 GRS. | C8421: 0857472006364
A8422: 790078 | B8422: PULP RIOT 6 VOL. DEVEL. 885 ML | C8422: EU SS6VOL
A8423: 790078 | B8423: PULP RIOT 6 VOL. DEVEL. 885 ML | C8423: 0857472006210
A8424: 790079 | B8424: PULP RIOT 10 VOL. DEVEL. 885 ML | C8424: EU SS10VOL
A8425: 790079 | B8425: PULP RIOT 10 VOL. DEVEL. 885 ML | C8425: 0857472006241
A8426: 790080 | B8426: PULP RIOT 20 VOL. DEVEL. 885 ML | C8426: EU SS20VOL
A8427: 790080 | B8427: PULP RIOT 20 VOL. DEVEL. 885 ML | C8427: 0857472006203
A8428: 790081 | B8428: PULP RIOT 30 VOL. DEVEL. 885 ML | C8428: EU SS30VOL
A8429: 790081 | B8429: PULP RIOT 30 VOL. DEVEL. 885 ML | C8429: 0857472006227
A8430: 790082 | B8430: PULP RIOT 40 VOL. DEVEL. 885 ML | C8430: EU SS40VOL
A8431: 790082 | B8431: PULP RIOT 40 VOL. DEVEL. 885 ML | C8431: 0857472006234
A8432: 790083 | B8432: PULP RIOT BARCELONA SH. 295 ML
A8433: 790083 | B8433: PULP RIOT BARCELONA SH. 295 ML | C8433: 0857472006388
A8434: 790084 | B8434: PULP RIOT BARCELONA SH. 975 ML
A8435: 790084 | B8435: PULP RIOT BARCELONA SH. 975 ML | C8435: 0857472006395
A8436: 790085 | B8436: PULP RIOT BANGKOK SH. 295 ML
A8437: 790085 | B8437: PULP RIOT BANGKOK SH. 295 ML | C8437: 0857472006449
A8438: 790086 | B8438: PULP RIOT BANGKOK SH. 975 ML
A8439: 790086 | B8439: PULP RIOT BANGKOK SH. 975 ML | C8439: 0857472006494
A8440: 790087 | B8440: PULP RIOT TOKYO COND. 295 ML
A8441: 790087 | B8441: PULP RIOT TOKYO COND. 295 ML | C8441: 0857472006456
A8442: 790088 | B8442: PULP RIOT TOKYO COND. 975 ML
A8443: 790088 | B8443: PULP RIOT TOKYO COND. 975 ML | C8443: 0857472006500
A8444: 799001 | B8444: INSTANT LINE SMOOTHER 19ML | C8444: GILS
A8445: 799002 | B8445: INSTANT LINE SMOOTHER 30ML | C8445: GILS30ML
A8446: 799003 | B8446: DREAM CREAM 50ML | C8446: GPM50ML
A8447: 799004 | B8447: DREAM CREAM 15ML | C8447: GPM15ML
A8448: 799005 | B8448: H'EYE'DRATOR EYE CREAM 15ML | C8448: GHEC
A8449: 799006 | B8449: LINE SMOOTHING CONCEALER-BEIGE | C8449: GLSC BE
A8450: 799007 | B8450: LINE SMOOTHING CONCEALER-HONEY | C8450: GLSC HO
A8451: 799008 | B8451: LINE SMOOTHING CONCEALER-IVORY | C8451: GLSC IV
A8452: 799009 | B8452: TRANSF. HIGHLIGHTING WAND | C8452: GTHW
A8453: 799010 | B8453: TRANSF. HIGHLIGHTING WAND DOU | C8453: GTHWD
A8454: 799011 | B8454: CASHMERE COLOR CORRECT. POWDER | C8454: GCCCP
... A8545: 980049 | B8545: CURSO BARBER'S CORNER VALENCIA | C8545: 0000000980049
A8546: KC3T | B8546: KINCREM 3 TUBOS ANTIGUO | C8546: KC3T
A8547: NC3T | B8547: NEW COLOR 3 TUBOS ANTIGUO | C8547: NC3T

Sheet BBDD ACTUALITZADA
A1: Nº | B1: Nombre | C1: CIF/NIF | D1: Dirección | E1: C.P. | F1: Población | G1: Provincia | H1: Nº teléfono | I1: Correo electrónico | J1: Cód. vendedor | K1: Importe Contrato Técnico | L1: Grupo registro IVA neg. | M1: Cód. términos pago | N1: Cód. Ruta | O1: Cód. transportista
A2: 9 | B2: DIST.CAROBEL'S CATALUÑA, S.L. | C2: B59945725 | D2: CL RELOJ, 7-9 | E2: 08923 | F2: SANTA COLOMA DE GRAMENET | G2: BARCELONA | H2: +34 933929352 | I2: distribucionescarobels@gmail.com | J2: 1004D | K2: 0 | L2: NACIONAL | M2: 4 | N2: PRL-900-11 | O2: 26 | P2: ES | Q2: NOEL BLANCO CURSA
A3: 31 | B3: EXCLUSIVAS NEGREDO S.L. | C3: B20223178 | D3: CL/ IRIBAR 6 C8-C9 POL.A.E. NEINOR | E3: 20018 | F3: GUIPUZCOA | G3: GUIPUZCOA | H3: +34 943492554 | I3: administracion@negredoprofesional.com; gerencia@negredoprofesional.com | J3: 1004D | K3: 0 | L3: NACIONAL | M3: 4 | N3: NOR-900-11 | O3: 22 | P3: ES | Q3: NOEL BLANCO CURSA
A4: 79 | B4: COMERCIAL PUJANTE S.L. | C4: B30094338 | D4: CL JUAN HERNÁNDEZ GONZÁLEZ, 2 | E4: 30565 | F4: LAS TORRES DE COTILLAS | G4: MURCIA | H4: +34 968620088 | I4: rafael.martinez@comercialpujante.com | J4: 1004D | K4: 0 | L4: NACIONAL | M4: 4 | N4: SUR-900-11 | O4: 22 | P4: ES | Q4: NOEL BLANCO CURSA
A5: 102 | B5: EXCLUSIVAS LADY'S S.L. | C5: B18089235 | D5: CL CASTILLA 39-40 | E5: 18210 | F5: PELIGROS | G5: GRANADA | H5: +34 958400177 | I5: plopez@exclusivasladys.com; info@exclusivasladys.com | J5: 1004D | K5: 0 | L5: NACIONAL | M5: 4 | N5: SUR-900-11 | O5: 22 | P5: ES | Q5: NOEL BLANCO CURSA
A6: 106 | B6: LARA SANCHEZ, FRANCISCO | C6: 34010807V | D6: AV LAS VENTAS 35 | E6: 14910 | F6: BENAMEJI | G6: CORDOBA | H6: +34 629888997 | I6: dislapefla@hotmail.com | J6: 1004D | K6: 0 | L6: NACIONAL | M6: 1-2PP | N6: SUR-900-11 | O6: 22 | P6: ES | Q6: NOEL BLANCO CURSA
A7: 155 | B7: EXCLUSIVAS J.J. SANCHEZ, S.L. | C7: B33805110 | D7: CL CORTES DE CADIZ 6 BIS BJ | E7: 33212 | F7: GIJON | G7: ASTURIAS | H7: +34 985338175 | I7: exclusivasjjsanchez@gmail.com | J7: 1004D | K7: 0 | L7: NACIONAL | M7: 4 | N7: NOR-900-11 | O7: 10 | P7: ES | Q7: NOEL BLANCO CURSA
A8: 199 | B8: COMERCIAL LOMARK, S.C.P. | C8: J60955119 | D8: CL/ CARRIL,17-19,4-BIS | E8: 08750 | F8: MOLINS DE REI | G8: BARCELONA | H8: +34 936683653 | I8: comerciallomark@gmail.com | J8: 1004D | K8: 0 | L8: NACIONAL | M8: 4 | N8: PRL-900-11 | O8: 26 | P8: ES | Q8: NOEL BLANCO CURSA
A9: 500 | B9: CEBRIAN, C.B. | C9: E02243426 | D9: CL PEDRO MARTINEZ GUTIERREZ 2 | E9: 02006 | F9: ALBACETE | G9: ALBACETE | H9: +34 967190388 | I9: cebriancb@outlook.com | J9: 1004D | K9: 0 | L9: NACREQ | M9: 4 | N9: SUR-900-11 | O9: 22 | P9: ES | Q9: NOEL BLANCO CURSA
A10: 544 | B10: PIQUET ORTEGA, SILVIA | C10: 40992757H | D10: CL VALENCIA 571 | E10: 08026 | F10: BARCELONA | G10: BARCELONA | H10: +34 932462948 | I10: silviapiquet22@hotmail.com | J10: 1004D | K10: 0 | L10: NACREQ | M10: 4 | N10: PRL-900-11 | O10: 26 | P10: ES | Q10: NOEL BLANCO CURSA
A11: 554 | B11: DOMINGUEZ RIVAS, Mª CARMEN | C11: 46637143C | D11: CL MAYOR 27 | E11: 08740 | F11: SANT ANDREU DE LA BARCA | G11: BARCELONA | H11: +34 600601739 | I11: lalunacomercial96@gmail.com | J11: 1004D | K11: 0 | L11: NACREQ | M11: 4 | N11: PRL-900-11 | O11: 26 | P11: ES | Q11: NOEL BLANCO CURSA
A12: 567 | B12: GRUP D'IMATGE JORDI, S.L. | C12: B17466483 | D12: CL PAGES I MORATO 23 | E12: 17200 | F12: PALAFRUGELL | G12: GIRONA | H12: +34 972302662 | I12: grupdimatgejordi@hotmail.com | J12: 1004D | K12: 0 | L12: NACIONAL | M12: 4 | N12: PRL-900-11 | O12: 10 | P12: ES | Q12: NOEL BLANCO CURSA
A13: 705 | B13: COOP. PELUQUEROS PALENTINOS | C13: F34152694 | D13: AV CARDENAL CISNEROS 22 | E13: 34002 | F13: PALENCIA | G13: PALENCIA | H13: +34 979710187 | I13: copepale@gmail.com | J13: 1004D | K13: 0 | L13: NACIONAL | M13: 4 | N13: NOR-900-11 | O13: 10 | P13: ES | Q13: NOEL BLANCO CURSA
... A103: 10697 | B103: GIRONA COSMETICS, SLP | C103: B16391062 | D103: RONDA FERRAN PUIG 23, LOCAL | E103: 17001 | F103: GIRONA | G103: GIRONA | H103: +34 607157640 | I103: GIRONACOSMETICS@GMAIL.COM | J103: 1004D | K103: 0 | L103: NACIONAL | M103: 4 | N103: PRL-900-11 | O103: 10 | P103: ES | Q103: NOEL BLANCO CURSA

Sheet T.P.
A1: CÓDIGO T.P. | B1: DESCRIPCIÓN T.P.
A2: 3 | B2: 30 DÍAS
A3: 4 | B3: 30-60 DÍAS
